Workbook
Name UPDATE: #REF!
Name UPDATE: #REF!
Name UPDATE: #REF!
Name UPDATE: #REF!
Name UPDATE: #REF!
Name UPDATE: #REF!
Name UPDATE: #REF!

Sheet Cover Page
E5: DABUR INDIA LTD.
E7: FINANCIAL MODEL AND BUSINESS VALUATION
E9: Company : Dabur India Ltd
E10: Ticker : NSE: Dabur | J10: xxxx | K10: Inputs / Assumptions
E11: Industry : FMCG | J11: xxxx | K11: Formulae
E12: Year Ending : March | J12: xxxx | K12: Linking/ Reference cell
E13: Analyst : Saurav Sarthak Das
E16: EIC Analysis'
E17: Full 3 FS Model & DCF'!A1 - 3statments
E18: Full 3 FS Model & DCF'!A89 - Supporting Schedules
E19: Full 3 FS Model & DCF'!A111 - Ratio & Assumptions
E20: Full 3 FS Model & DCF'!A130 - DCF Analysis
E21: Full 3 FS Model & DCF'!A177 - Sensitivity Analysis
E22: Other Key Financial Ratio'!A6
E23: Common-Size Statement'!A9
E24: Comp- Valuation- Dabur'!A6
E25: WACC Calculation'!A6
E26: Football Field Analysis'!A6
... E31: Recommendation!A6

Sheet EIC Analysis
B1: Dabur India Ltd.
B4: EIC Analysis
B6: EIC Analysis - Dabur India Ltd.
B7: Parent Company | C7: Dabur India Limited (Burman Family)
B8: Category | C8: Consumer Products, Healthcare, Personal Care, Food & Beverages
B9: Sector | C9: FMCG
B10: Tagline/ Slogan | C10: Celebrate Life
B11: USP | C11: Dabur is India’s largest Ayurvedic and natural healthcare FMCG company with strong heritage, wide rural reach, and a diversified portfolio across health supplements, personal care, home care, and foods.
B13: Economic Analysis - Dabur India Ltd.
B14: Real GDP or Gross Domestic Product (GDP) at constant (2011–12) prices for 2024–25 is projected to reach ₹175–178 trillion, supported by resilient domestic consumption, robust manufacturing activity, and strong government capital expenditure. India remains one of the fastest-growing major economies, with the IMF forecasting 6.8% GDP growth for FY25, reflecting broad-based economic momentum and stable macroeconomic fundamentals.
B16: According to the latest estimates, India continues to strengthen its global economic position. The country has emerged as the world’s third-largest startup ecosystem, with rising investments in technology, digital services, and consumer-focused sectors. The expanding innovation ecosystem is expected to generate large-scale employment and boost consumer demand—an important growth driver for FMCG companies like Dabur.
B19: To sustain high economic growth through 2030, India needs to create significant employment opportunities. As per McKinsey Global Institute, India must generate 8–9 million non-farm jobs annually to maintain productivity and achieve 7–8% GDP growth through the remainder of the decade. Improving rural income levels, favorable monsoon trends, and rising government spending on agriculture and rural infrastructure are expected to boost rural consumption, directly benefitting Dabur, which has one of the deepest rural distribution networks in the FMCG sector.
B27: Industry Analysis - Dabur India Ltd.
B29: STP of Dabur
B30: Segment | C30: Ayurvedic, natural and herbal healthcare products, personal care, home care, and food & beverage products for daily use
B31: Target Group | C31: Health-conscious consumers, families across urban and rural India, and individuals seeking natural, herbal, and immunity-focused products
B32: Positioning | C32: India’s most trusted Ayurvedic and natural wellness FMCG brand offering science-based, nature-derived products that promote holistic health and everyday well-being
B34: SWOT ANALYSIS
B55: PESTEL ANALYSIS
B73: PORTER'S FIVE FORCES ANALYSIS
B75: Competition Rivalry (High)
B76: Dabur faces intense competition from major FMCG players such as HUL, Patanjali, Emami, Marico, Baidyanath, and ITC. Most competitors offer similar Ayurvedic, natural, and healthcare products, making product switching easy for consumers.In segments like honey, oral care, juices, and healthcare supplements, multiple brands compete aggressively, increasing advertising and pricing pressures.
B80: Threat of new entrants (Moderate)
B81: While the FMCG sector is easy to enter at a small scale, building a trusted Ayurvedic brand like Dabur is challenging due to: High cost of brand building,Extensive distribution networks required,Regulatory approvals for health productsHowever, growing demand for natural and Ayurvedic products continues to attract start-ups and D2C wellness brands, keeping the threat at a moderate level.
B85: Threat of substitutes (Moderate-High)
B86: Consumers are increasingly shifting towards: Local Ayurvedic brands Herbal home remedies Organic and specialty wellness products In segments like honey, chyawanprash, and juices, substitutes are widely available. The wellness industry is expanding rapidly, increasing alternatives, but Dabur’s strong trust and legacy reduce the risk slightly.
B90: Bargaining power of suppliers (Low-Moderate)
B91: Dabur sources raw materials like herbs, fruits, and natural ingredients largely from domestic suppliers. Because most ingredients have many alternate suppliers, the bargaining power remains low. However, for specific herbs and organic-certified materials, supplier dependency can increase, making overall power low to moderate.
B94: Bargaining power of consumers (High)
... B101: Dabur India Ltd is one of the largest Ayurvedic and natural FMCG companies in India, with a legacy of over 140 years. The company operates across healthcare, personal care, home care, and food & beverages, with trusted brands such as Dabur Honey, Dabur Amla, Vatika, Real Juices, Dabur Red Toothpaste, Chyawanprash, and Pudin Hara. Dabur reaches over 6.9 million retail outlets and has a strong footprint in both urban and rural markets, including deep distribution in Tier-2 and Tier-3 regions. It also has a strong international presence across the Middle East, Africa, SAARC, and the US. With a market capitalization of USD 10–11 billion, Dabur is among the top Indian FMCG players and a global leader in Ayurvedic healthcare products. Its portfolio strongly aligns with growing wellness trends and the shift toward natural, herbal, and immunity-boosting products.
B115: Revenue from each segment | C115: Percent(%)
B116: Consumer Care Business | C116: 0.55
B117: Food & Beverages Business | C117: 0.155
B118: Other Segments | C118: 0.03
B119: International Business | C119: 0.265
B122: Back to cover

Sheet Full 3 FS Model & DCF
A1: Dabur India Ltd. | J1: Historical Period | P1: Forecasted Period
A4: Financial Statements | J4: 2020 | K4: =J4+1 -> 2021 | L4: =K4+1 -> 2022 | M4: =L4+1 -> 2023 | N4: =M4+1 -> 2024 | O4: =N4+1 -> 2025 | P4: =O4+1 -> 2026 | Q4: =P4+1 -> 2027 | R4: =Q4+1 -> 2028 | ... T4: =S4+1 -> 2030
A6: Income Statement
C7: (All figures in INR crores)
B9: Income
C10: Revenue | J10: ='Historical Statement'!H9 -> 8703.59 | K10: ='Historical Statement'!I9 -> 9561.65 | L10: ='Historical Statement'!J9 -> 10888.68 | M10: ='Historical Statement'!K9 -> 11529.89 | N10: ='Historical Statement'!L9 -> 12404.01 | O10: ='Historical Statement'!M9 -> 12563.09 | P10: =O10*(1+P115) -> 13530.196 | Q10: =P10*(1+Q115) -> 14519.672 | R10: =Q10*(1+R115) -> 15528.417 | S10: =R10*(1+S115) -> 16553.303 | T10: =S10*(1+T115) -> 17591.205
C11: Cost of Good Sold | J11: =-SUM('Historical Statement'!H13:H16) -> -4360.24 | K11: =-SUM('Historical Statement'!I13:I16) -> -4788.96 | L11: =-SUM('Historical Statement'!J13:J16) -> -5639.69 | M11: =-SUM('Historical Statement'!K13:K16) -> -6268.67 | N11: =-SUM('Historical Statement'!L13:L16) -> -6446.96 | O11: =-SUM('Historical Statement'!M13:M16) -> -6534.86 | P11: =-P10*O118 -> -7037.9131 | Q11: =-Q10*P118 -> -7509.9658 | R11: =-R10*Q118 -> -8031.7161 | S11: =-S10*R118 -> -8561.8147 | T11: =-T10*S118 -> -9098.6459
C12: Gross Profit | J12: =SUM(J10:J11) -> 4343.35 | K12: =SUM(K10:K11) -> 4772.69 | L12: =SUM(L10:L11) -> 5248.99 | M12: =SUM(M10:M11) -> 5261.22 | N12: =SUM(N10:N11) -> 5957.05 | O12: =SUM(O10:O11) -> 6028.23 | P12: =SUM(P10:P11) -> 6492.2827 | Q12: =SUM(Q10:Q11) -> 7009.7058 | ... T12: =SUM(T10:T11) -> 8492.5595
B13: Expenses
C14: Salaries and Benefit expenses | J14: =-'Historical Statement'!H17 -> -947.74 | K14: =-'Historical Statement'!I17 -> -1033.46 | L14: =-'Historical Statement'!J17 -> -1079.95 | M14: =-'Historical Statement'!K17 -> -1137 | N14: =-'Historical Statement'!L17 -> -1239.56 | O14: =-'Historical Statement'!M17 -> -1291.23 | P14: =-P10*P120 -> -1392.439 | Q14: =-Q10*Q120 -> -1494.2694 | R14: =-R10*R120 -> -1598.0828 | S14: =-S10*S120 -> -1703.5574 | T14: =-T10*T120 -> -1810.3715
C15: Other Expenses | J15: =-'Historical Statement'!H20 -> -1603.26 | K15: =-'Historical Statement'!I20 -> -1736.55 | L15: =-'Historical Statement'!J20 -> -1915.23 | M15: =-'Historical Statement'!K20 -> -1960.1 | N15: =-'Historical Statement'!L20 -> -2317.26 | O15: =-'Historical Statement'!M20 -> -2420.66 | P15: =-P10*P123 -> -2460.7188 | Q15: =-Q10*Q123 -> -2640.6735 | R15: =-R10*R123 -> -2824.1326 | S15: =-S10*S123 -> -3010.5273 | T15: =-T10*T123 -> -3199.2892
C16: EBITDA | J16: =SUM(J12:J15) -> 1792.35 | K16: =SUM(K12:K15) -> 2002.68 | L16: =SUM(L12:L15) -> 2253.81 | M16: =SUM(M12:M15) -> 2164.12 | N16: =SUM(N12:N15) -> 2400.23 | O16: =SUM(O12:O15) -> 2316.34 | P16: =SUM(P12:P15) -> 2639.1249 | Q16: =SUM(Q12:Q15) -> 2874.763 | ... T16: =SUM(T12:T15) -> 3482.8988
C17: Depreciation and amortisation expense | J17: =-'Historical Statement'!H19 -> -220.45 | K17: =-'Historical Statement'!I19 -> -240.13 | L17: =-'Historical Statement'!J19 -> -252.89 | M17: =-'Historical Statement'!K19 -> -310.96 | N17: =-'Historical Statement'!L19 -> -399.21 | O17: =-'Historical Statement'!M19 -> -445.6 | P17: =P101 -> -466.09181 | Q17: =Q101 -> -439.43245 | R17: =R101 -> -413.13186 | S17: =S101 -> -387.675 | T17: =T101 -> -363.33744
C18: EBIT | J18: =SUM(J16:J17) -> 1571.9 | K18: =SUM(K16:K17) -> 1762.55 | L18: =SUM(L16:L17) -> 2000.92 | M18: =SUM(M16:M17) -> 1853.16 | N18: =SUM(N16:N17) -> 2001.02 | O18: =SUM(O16:O17) -> 1870.74 | P18: =SUM(P16:P17) -> 2173.0331 | Q18: =SUM(Q16:Q17) -> 2435.3306 | ... T18: =SUM(T16:T17) -> 3119.5614
C19: Interest | J19: =-'Historical Statement'!H18 -> -49.54 | K19: =-'Historical Statement'!I18 -> -30.81 | L19: =-'Historical Statement'!J18 -> -38.6 | M19: =-'Historical Statement'!K18 -> -78.24 | N19: =-'Historical Statement'!L18 -> -124.18 | O19: =-'Historical Statement'!M18 -> -163.5 | P19: =P108 -> -109.03195 | Q19: =Q108 -> -109.03195 | R19: =R108 -> -109.03195 | S19: =S108 -> -109.03195 | T19: =T108 -> -109.03195
C20: Other Income (Expenses) | J20: =SUM('Historical Statement'!H10+'Historical Statement'!H26) -> 205.29 | K20: =SUM('Historical Statement'!I10+'Historical Statement'!I26) -> 325.29 | L20: =SUM('Historical Statement'!J10+'Historical Statement'!J26) -> 308.16 | M20: =SUM('Historical Statement'!K10+'Historical Statement'!K26) -> 445.39 | N20: =SUM('Historical Statement'!L10+'Historical Statement'!L26) -> 482.41 | O20: =SUM('Historical Statement'!M10+'Historical Statement'!M26) -> 550.1 | P20: =P10*P132 -> 467.27809 | Q20: =Q10*Q132 -> 501.45057 | R20: =R10*R132 -> 536.28854 | S20: =S10*S132 -> 571.68394 | T20: =T10*T132 -> 607.52889
C21: Earning Before Tax | J21: =SUM(J18:J20) -> 1727.65 | K21: =SUM(K18:K20) -> 2057.03 | L21: =SUM(L18:L20) -> 2270.48 | M21: =SUM(M18:M20) -> 2220.31 | N21: =SUM(N18:N20) -> 2359.25 | O21: =SUM(O18:O20) -> 2257.34 | P21: =SUM(P18:P20) -> 2531.2793 | Q21: =SUM(Q18:Q20) -> 2827.7492 | ... T21: =SUM(T18:T20) -> 3618.0583
C22: Tax | J22: =-'Historical Statement'!H31 -> -279.72 | K22: =-'Historical Statement'!I31 -> -361.07 | L22: =-'Historical Statement'!J31 -> -526.38 | M22: =-'Historical Statement'!K31 -> -517.35 | N22: =-'Historical Statement'!L31 -> -547.43 | O22: =-'Historical Statement'!M31 -> -517.47 | P22: =-P21*P135 -> -533.06904 | Q22: =-Q21*Q135 -> -595.50345 | R22: =-R21*R135 -> -650.43888 | S22: =-S21*S135 -> -705.987 | T22: =-T21*T135 -> -761.93682
C23: Net Profit | J23: =SUM(J21:J22) -> 1447.93 | K23: =SUM(K21:K22) -> 1695.96 | L23: =SUM(L21:L22) -> 1744.1 | M23: =SUM(M21:M22) -> 1702.96 | N23: =SUM(N21:N22) -> 1811.82 | O23: =SUM(O21:O22) -> 1739.87 | P23: =SUM(P21:P22) -> 1998.2102 | Q23: =SUM(Q21:Q22) -> 2232.2457 | ... T23: =SUM(T21:T22) -> 2856.1215
A25: Balance Sheet
B27: Assets
C28: Current Assets:
D29: Cash | J29: ='Historical Statement'!H64 -> 163.94 | K29: ='Historical Statement'!I64 -> 241.23 | L29: ='Historical Statement'!J64 -> 255.91 | M29: ='Historical Statement'!K64 -> 146.82 | N29: ='Historical Statement'!L64 -> 247.6 | O29: ='Historical Statement'!M64 -> 111.97 | P29: =P87 -> 1063.201 | Q29: =Q87 -> 2380.0817 | R29: =R87 -> 3797.5188 | S29: =S87 -> 5312.9126 | T29: =T87 -> 6926.0365
D30: Bank deposits | J30: ='Historical Statement'!H65 -> 647.43 | K30: ='Historical Statement'!I65 -> 1087.8 | L30: ='Historical Statement'!J65 -> 314.23 | M30: ='Historical Statement'!K65 -> 179.1 | N30: ='Historical Statement'!L65 -> 418.76 | O30: ='Historical Statement'!M65 -> 393.74 | P30: =O30 -> 393.74 | Q30: =P30 -> 393.74 | R30: =Q30 -> 393.74 | S30: =R30 -> 393.74 | T30: =S30 -> 393.74
D31: Accounts Receivables | J31: ='Historical Statement'!H63 -> 813.89 | K31: ='Historical Statement'!I63 -> 561.58 | L31: ='Historical Statement'!J63 -> 646.15 | M31: ='Historical Statement'!K63 -> 848.75 | N31: ='Historical Statement'!L63 -> 898.72 | O31: ='Historical Statement'!M63 -> 888.5 | P31: =(P10*P141)/365 -> 966.00192 | Q31: =(Q10*Q141)/365 -> 1036.6465 | R31: =(R10*R141)/365 -> 1108.6669 | S31: =(S10*S141)/365 -> 1181.8397 | T31: =(T10*T141)/365 -> 1255.9418
D32: Inventory | J32: ='Historical Statement'!H60 -> 1379.57 | K32: ='Historical Statement'!I60 -> 1734.28 | L32: ='Historical Statement'!J60 -> 1911.37 | M32: ='Historical Statement'!K60 -> 2024.2 | N32: ='Historical Statement'!L60 -> 1946.97 | O32: ='Historical Statement'!M60 -> 2300.11 | P32: =-(P11*P147)/365 -> 2339.3248 | Q32: =-(Q11*Q147)/365 -> 2496.23 | R32: =-(R11*R147)/365 -> 2669.654 | S32: =-(S11*S147)/365 -> 2845.853 | T32: =-(T11*T147)/365 -> 3024.2898
D33: Other Current Assets | J33: ='Historical Statement'!H69+'Historical Statement'!H68 -> 468.44 | K33: ='Historical Statement'!I69+'Historical Statement'!I68 -> 387.36 | L33: ='Historical Statement'!J69+'Historical Statement'!J68 -> 298.11 | M33: ='Historical Statement'!K69+'Historical Statement'!K68 -> 284.65 | N33: ='Historical Statement'!L69+'Historical Statement'!L68 -> 458.46 | O33: ='Historical Statement'!M69+'Historical Statement'!M68 -> 634.27 | P33: =O33 -> 634.27 | Q33: =P33 -> 634.27 | R33: =Q33 -> 634.27 | S33: =R33 -> 634.27 | T33: =S33 -> 634.27
C35: Non-current Assets:
D36: Property, plant and equipment | J36: ='Historical Statement'!H43+'Historical Statement'!H44+'Historical Statement'!H45+'Historical Statement'!H47+'Historical Statement'!H48 -> 2063.28 | K36: ='Historical Statement'!I43+'Historical Statement'!I44+'Historical Statement'!I45+'Historical Statement'!I47+'Historical Statement'!I48 -> 2054.21 | L36: ='Historical Statement'!J43+'Historical Statement'!J44+'Historical Statement'!J45+'Historical Statement'!J47+'Historical Statement'!J48 -> 2224.25 | M36: ='Historical Statement'!K43+'Historical Statement'!K44+'Historical Statement'!K45+'Historical Statement'!K47+'Historical Statement'!K48 -> 3348.53 | N36: ='Historical Statement'!L43+'Historical Statement'!L44+'Historical Statement'!L45+'Historical Statement'!L47+'Historical Statement'!L48 -> 3642.11 | O36: ='Historical Statement'!M43+'Historical Statement'!M44+'Historical Statement'!M45+'Historical Statement'!M47+'Historical Statement'!M48 -> 3753.59 | P36: =P102 -> 3538.8935 | Q36: =Q102 -> 3327.0861 | R36: =R102 -> 3122.0738 | S36: =S102 -> 2926.0754 | T36: =T102 -> 2740.2496
D37: Goodwill | J37: ='Historical Statement'!H46 -> 335.97 | K37: ='Historical Statement'!I46 -> 336.01 | L37: ='Historical Statement'!J46 -> 251.15 | M37: ='Historical Statement'!K46 -> 405.25 | N37: ='Historical Statement'!L46 -> 405.12 | O37: ='Historical Statement'!M46 -> 405.09 | P37: =O37 -> 405.09 | Q37: =P37 -> 405.09 | R37: =Q37 -> 405.09 | S37: =R37 -> 405.09 | T37: =S37 -> 405.09
D38: Financial Assets | J38: ='Historical Statement'!H51+'Historical Statement'!H52+'Historical Statement'!H53+'Historical Statement'!H62+'Historical Statement'!H66+'Historical Statement'!H67+'Historical Statement'!H71+'Historical Statement'!H49 -> 3369.34 | K38: ='Historical Statement'!I51+'Historical Statement'!I52+'Historical Statement'!I53+'Historical Statement'!I62+'Historical Statement'!I66+'Historical Statement'!I67+'Historical Statement'!I71+'Historical Statement'!I49 -> 4288.44 | L38: ='Historical Statement'!J51+'Historical Statement'!J52+'Historical Statement'!J53+'Historical Statement'!J62+'Historical Statement'!J66+'Historical Statement'!J67+'Historical Statement'!J71+'Historical Statement'!J49 -> 6279.45 | M38: ='Historical Statement'!K51+'Historical Statement'!K52+'Historical Statement'!K53+'Historical Statement'!K62+'Historical Statement'!K66+'Historical Statement'!K67+'Historical Statement'!K71+'Historical Statement'!K49 -> 6324.62 | N38: ='Historical Statement'!L51+'Historical Statement'!L52+'Historical Statement'!L53+'Historical Statement'!L62+'Historical Statement'!L66+'Historical Statement'!L67+'Historical Statement'!L71+'Historical Statement'!L49 -> 6996.03 | O38: ='Historical Statement'!M51+'Historical Statement'!M52+'Historical Statement'!M53+'Historical Statement'!M62+'Historical Statement'!M66+'Historical Statement'!M67+'Historical Statement'!M71+'Historical Statement'!M49 -> 7533.27 | P38: =O38 -> 7533.27 | Q38: =P38 -> 7533.27 | R38: =Q38 -> 7533.27 | S38: =R38 -> 7533.27 | T38: =S38 -> 7533.27
D39: Other Non-current Assets | J39: =SUM('Historical Statement'!H54:H56) -> 112.15 | K39: =SUM('Historical Statement'!I54:I56) -> 156.22 | L39: =SUM('Historical Statement'!J54:J56) -> 103.91 | M39: =SUM('Historical Statement'!K54:K56) -> 92.45 | N39: =SUM('Historical Statement'!L54:L56) -> 108.91 | O39: =SUM('Historical Statement'!M54:M56) -> 139.44 | P39: =O39 -> 139.44 | Q39: =P39 -> 139.44 | R39: =Q39 -> 139.44 | S39: =R39 -> 139.44 | T39: =S39 -> 139.44
D40: Total Assets | J40: =SUM(J29:J39) -> 9354.01 | K40: =SUM(K29:K39) -> 10847.13 | L40: =SUM(L29:L39) -> 12284.53 | M40: =SUM(M29:M39) -> 13654.37 | N40: =SUM(N29:N39) -> 15122.68 | O40: =SUM(O29:O39) -> 16159.98 | P40: =SUM(P29:P39) -> 17013.231 | Q40: =SUM(Q29:Q39) -> 18345.854 | ... T40: =SUM(T29:T39) -> 23052.328
B42: Liability
C43: Current Liabilities
D44: Accounts Payable | J44: =SUM('Historical Statement'!H98:H99) -> 1482.15 | K44: =SUM('Historical Statement'!I98:I99) -> 1915.26 | L44: =SUM('Historical Statement'!J98:J99) -> 2017.95 | M44: =SUM('Historical Statement'!K98:K99) -> 2186.61 | N44: =SUM('Historical Statement'!L98:L99) -> 2421.71 | O44: =SUM('Historical Statement'!M98:M99) -> 2825.34 | P44: =-(P11*P144)/365 -> 2644.4595 | Q44: =-(Q11*Q144)/365 -> 2821.8309 | R44: =-(R11*R144)/365 -> 3017.8759 | S44: =-(S11*S144)/365 -> 3217.0577 | T44: =-(T11*T144)/365 -> 3418.7693
D45: Other Current Liabilities | J45: =SUM('Historical Statement'!H100:H103) -> 677.49 | K45: =SUM('Historical Statement'!I100:I103) -> 644 | L45: =SUM('Historical Statement'!J100:J103) -> 664.43 | M45: =SUM('Historical Statement'!K100:K103) -> 692.23 | N45: =SUM('Historical Statement'!L100:L103) -> 849.87 | O45: =SUM('Historical Statement'!M100:M103) -> 1028.68 | P45: =O45 -> 1028.68 | Q45: =P45 -> 1028.68 | R45: =Q45 -> 1028.68 | S45: =R45 -> 1028.68 | T45: =S45 -> 1028.68
C46: Non-Current Liabilities
D47: Debt | J47: ='Historical Statement'!H86+'Historical Statement'!H87+'Historical Statement'!H95+'Historical Statement'!H96 -> 467.13 | K47: ='Historical Statement'!I86+'Historical Statement'!I87+'Historical Statement'!I95+'Historical Statement'!I96 -> 509.06 | L47: ='Historical Statement'!J86+'Historical Statement'!J87+'Historical Statement'!J95+'Historical Statement'!J96 -> 1030.1 | M47: ='Historical Statement'!K86+'Historical Statement'!K87+'Historical Statement'!K95+'Historical Statement'!K96 -> 1173.79 | N47: ='Historical Statement'!L86+'Historical Statement'!L87+'Historical Statement'!L95+'Historical Statement'!L96 -> 1365.09 | O47: ='Historical Statement'!M86+'Historical Statement'!M87+'Historical Statement'!M95+'Historical Statement'!M96 -> 878.07 | P47: =P107 -> 878.07 | Q47: =Q107 -> 878.07 | R47: =R107 -> 878.07 | S47: =S107 -> 878.07 | T47: =T107 -> 878.07
D48: Other Non-Current Liabilities | J48: ='Historical Statement'!H88+'Historical Statement'!H89+'Historical Statement'!H90 -> 85.03 | K48: ='Historical Statement'!I88+'Historical Statement'!I89+'Historical Statement'!I90 -> 78.59 | L48: ='Historical Statement'!J88+'Historical Statement'!J89+'Historical Statement'!J90 -> 150.2 | M48: ='Historical Statement'!K88+'Historical Statement'!K89+'Historical Statement'!K90 -> 160.31 | N48: ='Historical Statement'!L88+'Historical Statement'!L89+'Historical Statement'!L90 -> 182.93 | O48: ='Historical Statement'!M88+'Historical Statement'!M89+'Historical Statement'!M90 -> 217.63 | P48: =O48 -> 217.63 | Q48: =P48 -> 217.63 | R48: =Q48 -> 217.63 | S48: =R48 -> 217.63 | T48: =S48 -> 217.63
D49: Total Liabilities | J49: =SUM(J44:J48) -> 2711.8 | K49: =SUM(K44:K48) -> 3146.91 | L49: =SUM(L44:L48) -> 3862.68 | M49: =SUM(M44:M48) -> 4212.94 | N49: =SUM(N44:N48) -> 4819.6 | O49: =SUM(O44:O48) -> 4949.72 | P49: =SUM(P44:P48) -> 4768.8395 | Q49: =SUM(Q44:Q48) -> 4946.2109 | ... T49: =SUM(T44:T48) -> 5543.1493
C51: Shareholder's Equity
D52: Equity Capital | J52: ='Historical Statement'!H77 -> 176.71 | K52: ='Historical Statement'!I77 -> 176.74 | L52: ='Historical Statement'!J77 -> 176.79 | M52: ='Historical Statement'!K77 -> 177.18 | N52: ='Historical Statement'!L77 -> 177.2 | O52: ='Historical Statement'!M77 -> 177.23 | P52: =O52 -> 177.23 | Q52: =P52 -> 177.23 | R52: =Q52 -> 177.23 | S52: =R52 -> 177.23 | T52: =S52 -> 177.23
D53: Retained Earnings | J53: ='Historical Statement'!H78 -> 6429.04 | K53: ='Historical Statement'!I78 -> 7486.79 | L53: ='Historical Statement'!J78 -> 8204.51 | M53: ='Historical Statement'!K78 -> 8796.08 | N53: ='Historical Statement'!L78 -> 9689.1 | O53: ='Historical Statement'!M78 -> 10623.46 | P53: =O53+P23+P79 -> 11657.592 | Q53: =P53+Q23+Q79 -> 12812.843 | R53: =Q53+R23+R79 -> 14074.668 | S53: =R53+S23+S79 -> 15444.253 | T53: =S53+T23+T79 -> 16922.378
D54: Total Shareholder's Equity | J54: =SUM(J52:J53) -> 6605.75 | K54: =SUM(K52:K53) -> 7663.53 | L54: =SUM(L52:L53) -> 8381.3 | M54: =SUM(M52:M53) -> 8973.26 | N54: =SUM(N52:N53) -> 9866.3 | O54: =SUM(O52:O53) -> 10800.69 | P54: =SUM(P52:P53) -> 11834.822 | Q54: =SUM(Q52:Q53) -> 12990.073 | ... T54: =SUM(T52:T53) -> 17099.608
D55: Non-controlling Interest | J55: ='Historical Statement'!H80 -> 36.46 | K55: ='Historical Statement'!I80 -> 36.69 | L55: ='Historical Statement'!J80 -> 40.55 | M55: ='Historical Statement'!K80 -> 468.17 | N55: ='Historical Statement'!L80 -> 436.78 | O55: ='Historical Statement'!M80 -> 409.57 | P55: =O55 -> 409.57 | Q55: =P55 -> 409.57 | R55: =Q55 -> 409.57 | S55: =R55 -> 409.57 | T55: =S55 -> 409.57
D56: Total Liabilities & Shareholder's Equity | J56: =J54+J49+J55 -> 9354.01 | K56: =K54+K49+K55 -> 10847.13 | L56: =L54+L49+L55 -> 12284.53 | M56: =M54+M49+M55 -> 13654.37 | N56: =N54+N49+N55 -> 15122.68 | O56: =O54+O49+O55 -> 16159.98 | P56: =P54+P49+P55 -> 17013.231 | Q56: =Q54+Q49+Q55 -> 18345.854 | ... T56: =T54+T49+T55 -> 23052.328
D58: Check | J58: =J56=J40 -> TRUE | K58: =K56=K40 -> TRUE | L58: =L56=L40 -> TRUE | M58: =IF(M40=M56,TRUE,FALSE) -> TRUE | N58: =IF(N40=N56,TRUE,FALSE) -> TRUE | O58: =IF(O40=O56,TRUE,FALSE) -> TRUE | P58: =IF(P40=P56,TRUE,FALSE) -> TRUE | Q58: =IF(Q40=Q56,TRUE,FALSE) -> TRUE | R58: =IF(R40=R56,TRUE,FALSE) -> TRUE | S58: =IF(S40=S56,TRUE,FALSE) -> TRUE | T58: =IF(T40=T56,TRUE,FALSE) -> TRUE
A60: Cashflow Statement
C62: Operating Cashflow
D63: Net Earnings | J63: ='Historical Statement'!H113 +'Historical Statement'!H141 -> 1418.7 | K63: ='Historical Statement'!I113 +'Historical Statement'!I141 -> 1734.7 | L63: ='Historical Statement'!J113 +'Historical Statement'!J141 -> 1881.08 | M63: ='Historical Statement'!K113 +'Historical Statement'!K141 -> 1724.23 | N63: ='Historical Statement'!L113 +'Historical Statement'!L141 -> 1864.82 | O63: ='Historical Statement'!M113 +'Historical Statement'!M141 -> 1853.35 | P63: =P23 -> 1998.2102 | Q63: =Q23 -> 2232.2457 | R63: =R23 -> 2438.1713 | S63: =S23 -> 2646.3935 | T63: =T23 -> 2856.1215
D64: Depreciation and amortisation expense | J64: ='Historical Statement'!H115 -> 220.45 | K64: ='Historical Statement'!I115 -> 240.13 | L64: ='Historical Statement'!J115 -> 252.89 | M64: ='Historical Statement'!K115 -> 310.96 | N64: ='Historical Statement'!L115 -> 399.21 | O64: ='Historical Statement'!M115 -> 445.6 | P64: =-P101 -> 466.09181 | Q64: =-Q101 -> 439.43245 | R64: =-R101 -> 413.13186 | S64: =-S101 -> 387.675 | T64: =-T101 -> 363.33744
D65: Pus/Less: Adjustment for Non-operating Items | J65: =SUM('Historical Statement'!H115:H130)-'Historical Statement'!H115 -> 32.46 | K65: =SUM('Historical Statement'!I115:I130)-'Historical Statement'!I115 -> -248.52 | L65: =SUM('Historical Statement'!J115:J130)-'Historical Statement'!J115 -> -234.86 | M65: =SUM('Historical Statement'!K115:K130)-'Historical Statement'!K115 -> -386.69 | N65: =SUM('Historical Statement'!L115:L130)-'Historical Statement'!L115 -> -351.7 | O65: =SUM('Historical Statement'!M115:M130)-'Historical Statement'!M115 -> -301.23 | P65: =-SUM(P19:P20) -> -358.24614 | Q65: =-SUM(Q19:Q20) -> -392.41862 | R65: =-SUM(R19:R20) -> -427.25659 | S65: =-SUM(S19:S20) -> -462.65199 | T65: =-SUM(T19:T20) -> -498.49694
D66: Pus/Less: Adjustment for operating assets & working capital | J66: =J96 -> -57.99 | K66: =K96 -> 388.36 | L66: =L96 -> -96.78 | M66: =M96 -> -160.07 | N66: =N96 -> 101.14 | O66: =O96 -> -10.97 | P66: =P96 -> -297.59722 | Q66: =Q96 -> -50.178375 | ... T66: =T96 -> -50.827325
D67: Cash From Operation | J67: =SUM(J63:J66) -> 1613.62 | K67: =SUM(K63:K66) -> 2114.67 | L67: =SUM(L63:L66) -> 1802.33 | M67: =SUM(M63:M66) -> 1488.43 | N67: =SUM(N63:N66) -> 2013.47 | O67: =SUM(O63:O66) -> 1986.75 | P67: =SUM(P63:P66) -> 1808.4587 | Q67: =SUM(Q63:Q66) -> 2229.0812 | ... T67: =SUM(T63:T66) -> 2670.1346
C69: Investing Cashflow
D70: Investments in Property & Equipment | J70: ='Historical Statement'!H145 -> -417.46 | K70: ='Historical Statement'!I145 -> -311.21 | L70: ='Historical Statement'!J145 -> -374.13 | M70: ='Historical Statement'!K145 -> -509.09 | N70: ='Historical Statement'!L145 -> -563.86 | O70: ='Historical Statement'!M145 -> -569.54 | P70: =-P100 -> -251.39526 | Q70: =-Q100 -> -227.62515 | R70: =-R100 -> -208.11946 | S70: =-S100 -> -191.67662 | T70: =-T100 -> -177.5117
D71: Sale of Property, Plant & Equipment | J71: ='Historical Statement'!H146 -> 16.97 | K71: ='Historical Statement'!I146 -> 4.88 | L71: ='Historical Statement'!J146 -> 4.93 | M71: ='Historical Statement'!K146 -> 23.38 | N71: ='Historical Statement'!L146 -> 2.98 | O71: ='Historical Statement'!M146 -> 30.43 | P71: =0 -> 0 | Q71: =0 -> 0 | R71: =0 -> 0 | S71: =0 -> 0 | T71: =0 -> 0
D72: Purchase/ sale of investments | J72: =SUM('Historical Statement'!H147:H149) -> -364.56 | K72: =SUM('Historical Statement'!I147:I149) -> -1361.06 | L72: =SUM('Historical Statement'!J147:J149) -> -1273.05 | M72: =SUM('Historical Statement'!K147:K149) -> -495.02 | N72: =SUM('Historical Statement'!L147:L149) -> -797.81 | O72: =SUM('Historical Statement'!M147:M149) -> -309.28 | P72: =O38-P38 -> 0 | Q72: =P38-Q38 -> 0 | R72: =Q38-R38 -> 0 | S72: =R38-S38 -> 0 | T72: =S38-T38 -> 0
D73: Interest Received | J73: ='Historical Statement'!H150 -> 248.21 | K73: ='Historical Statement'!I150 -> 261.61 | L73: ='Historical Statement'!J150 -> 366.8 | M73: ='Historical Statement'!K150 -> 394.19 | N73: ='Historical Statement'!L150 -> 386.95 | O73: ='Historical Statement'!M150 -> 399.28 | P73: =P20 -> 467.27809 | Q73: =Q20 -> 501.45057 | R73: =R20 -> 536.28854 | S73: =S20 -> 571.68394 | T73: =T20 -> 607.52889
D74: Cash From Investing | J74: =SUM(J70:J73) -> -516.84 | K74: =SUM(K70:K73) -> -1405.78 | L74: =SUM(L70:L73) -> -1275.45 | M74: =SUM(M70:M73) -> -586.54 | N74: =SUM(N70:N73) -> -971.74 | O74: =SUM(O70:O73) -> -449.11 | P74: =SUM(P70:P73) -> 215.88283 | Q74: =SUM(Q70:Q73) -> 273.82542 | ... T74: =SUM(T70:T73) -> 430.01719
C76: Financing Cashflow
D77: Issuance(Repayment) of Debt | J77: =SUM('Historical Statement'!H155:H160) -> -396.76 | K77: =SUM('Historical Statement'!I155:I160) -> -2 | L77: =SUM('Historical Statement'!J155:J160) -> 503.63 | M77: =SUM('Historical Statement'!K155:K160) -> 12.68 | N77: =SUM('Historical Statement'!L155:L160) -> -88.77 | O77: =SUM('Historical Statement'!M155:M160) -> -265.82 | P77: =P106 -> 0 | Q77: =Q106 -> 0 | R77: =R106 -> 0 | S77: =S106 -> 0 | T77: =T106 -> 0
D78: Issuance(Repayment) of NCI | J78: ='Historical Statement'!H161 -> 0 | K78: ='Historical Statement'!I161 -> 0 | L78: ='Historical Statement'!J161 -> - | M78: ='Historical Statement'!K161 -> -49.1 | N78: ='Historical Statement'!L161 -> - | O78: ='Historical Statement'!M161 -> 0 | P78: 0 | Q78: 0 | R78: 0 | S78: 0 | T78: 0
D79: Dividend Paid | J79: ='Historical Statement'!H162 -> -512.45 | K79: ='Historical Statement'!I162 -> -592.09 | L79: ='Historical Statement'!J162 -> -972.32 | M79: ='Historical Statement'!K162 -> -921.31 | N79: ='Historical Statement'!L162 -> -965.76 | O79: ='Historical Statement'!M162 -> -974.78 | P79: =-P23*P138 -> -964.07859 | Q79: =-Q23*Q138 -> -1076.994 | R79: =-R23*R138 -> -1176.3471 | S79: =-S23*S138 -> -1276.8083 | T79: =-T23*T138 -> -1377.9959
D80: Interest Paid | J80: ='Historical Statement'!H164 -> -28.51 | K80: ='Historical Statement'!I164 -> -19.35 | L80: ='Historical Statement'!J164 -> -21.85 | M80: ='Historical Statement'!K164 -> -77.9 | N80: ='Historical Statement'!L164 -> -106.68 | O80: ='Historical Statement'!M164 -> -164.77 | P80: =P108 -> -109.03195 | Q80: =Q108 -> -109.03195 | R80: =R108 -> -109.03195 | S80: =S108 -> -109.03195 | T80: =T108 -> -109.03195
D81: Dividend Distribution Tax | J81: ='Historical Statement'!H163 -> -105.33 | K81: ='Historical Statement'!I163 -> 0 | L81: ='Historical Statement'!J163 -> 0 | M81: ='Historical Statement'!K163 -> 0 | N81: ='Historical Statement'!L163 -> 0 | O81: ='Historical Statement'!M163 -> 0 | P81: =0 -> 0 | Q81: =0 -> 0 | R81: =0 -> 0 | S81: =0 -> 0 | T81: =0 -> 0
D82: Issuance(Repayment) of Equity | J82: ='Historical Statement'!H154 -> 0.08 | K82: ='Historical Statement'!I154 -> 0.03 | L82: ='Historical Statement'!J154 -> 0.05 | M82: ='Historical Statement'!K154 -> 0.39 | N82: ='Historical Statement'!L154 -> 0.03 | O82: ='Historical Statement'!M154 -> 0.03 | P82: =0 -> 0 | Q82: =0 -> 0 | R82: =0 -> 0 | S82: =0 -> 0 | T82: =0 -> 0
D83: Cash From Investing | J83: =SUM(J77:J82) -> -1042.97 | K83: =SUM(K77:K82) -> -613.41 | L83: =SUM(L77:L82) -> -490.49 | M83: =SUM(M77:M82) -> -1035.24 | N83: =SUM(N77:N82) -> -1161.18 | O83: =SUM(O77:O82) -> -1405.34 | P83: =SUM(P77:P82) -> -1073.1105 | Q83: =SUM(Q77:Q82) -> -1186.0259 | ... T83: =SUM(T77:T82) -> -1487.0279
D85: Net Increase (Decrease) in Cash | J85: =J67+J74+J83 -> 53.81 | K85: =K67+K74+K83 -> 95.48 | L85: =L67+L74+L83 -> 36.39 | M85: =M67+M74+M83 -> -133.35 | N85: =N67+N74+N83 -> -119.45 | O85: =O67+O74+O83 -> 132.3 | P85: =P83+P74+P67 -> 951.23096 | Q85: =Q83+Q74+Q67 -> 1316.8807 | R85: =R83+R74+R67 -> 1417.4371 | S85: =S83+S74+S67 -> 1515.3937 | T85: =T83+T74+T67 -> 1613.124
D86: Opening Cash Balance | J86: =SUM('Historical Statement'!H168:H170) -> 37.93 | K86: =SUM('Historical Statement'!I168:I170) -> 93.3 | L86: =SUM('Historical Statement'!J168:J170) -> 190.78 | M86: =SUM('Historical Statement'!K168:K170) -> 230.92 | N86: =SUM('Historical Statement'!L168:L170) -> 98.27 | O86: =SUM('Historical Statement'!M168:M170) -> -20.33 | P86: =O87 -> 111.97 | Q86: =P87 -> 1063.201 | R86: =Q87 -> 2380.0817 | S86: =R87 -> 3797.5188 | T86: =S87 -> 5312.9126
D87: Closing Cash Balance | J87: =SUM(J85:J86) -> 91.74 | K87: =SUM(K85:K86) -> 188.78 | L87: =SUM(L85:L86) -> 227.17 | M87: =SUM(M85:M86) -> 97.57 | N87: =SUM(N85:N86) -> -21.18 | O87: =SUM(O85:O86) -> 111.97 | P87: =SUM(P85:P86) -> 1063.201 | Q87: =SUM(Q85:Q86) -> 2380.0817 | ... T87: =SUM(T85:T86) -> 6926.0365
A89: Supporting Schedules
C91: Working Capital
D92: Account Receivables | J92: ='Historical Statement'!H134 -> 14.28 | K92: ='Historical Statement'!I134 -> 247.79 | L92: ='Historical Statement'!J134 -> -78.37 | M92: ='Historical Statement'!K134 -> -190.79 | N92: ='Historical Statement'!L134 -> -55.34 | O92: ='Historical Statement'!M134 -> 12.22 | P92: =O31-P31 -> -77.501919 | Q92: =P31-Q31 -> -70.644623 | R92: =Q31-R31 -> -72.020384 | S92: =R31-S31 -> -73.172758 | T92: =S31-T31 -> -74.102098
D93: Inventory | J93: ='Historical Statement'!H133 -> -79.02 | K93: ='Historical Statement'!I133 -> -354.71 | L93: ='Historical Statement'!J133 -> -177.1 | M93: ='Historical Statement'!K133 -> -96.02 | N93: ='Historical Statement'!L133 -> 77.24 | O93: ='Historical Statement'!M133 -> -353.14 | P93: =O32-P32 -> -39.214847 | Q93: =P32-Q32 -> -156.90514 | R93: =Q32-R32 -> -173.42405 | S93: =R32-S32 -> -176.19895 | T93: =S32-T32 -> -178.43679
D94: Accounts Payables | J94: ='Historical Statement'!H137 -> 25.99 | K94: ='Historical Statement'!I137 -> 433.78 | L94: ='Historical Statement'!J137 -> 108.01 | M94: ='Historical Statement'!K137 -> 141.3 | N94: ='Historical Statement'!L137 -> 216.57 | O94: ='Historical Statement'!M137 -> 407.18 | P94: =P44-O44 -> -180.88045 | Q94: =Q44-P44 -> 177.37138 | R94: =R44-Q44 -> 196.04498 | S94: =S44-R44 -> 199.18183 | T94: =T44-S44 -> 201.71156
D95: Others | J95: =SUM('Historical Statement'!H135,'Historical Statement'!H136,'Historical Statement'!H138,'Historical Statement'!H139) -> -19.24 | K95: =SUM('Historical Statement'!I135,'Historical Statement'!I136,'Historical Statement'!I138,'Historical Statement'!I139) -> 61.5 | L95: =SUM('Historical Statement'!J135,'Historical Statement'!J136,'Historical Statement'!J138,'Historical Statement'!J139) -> 50.68 | M95: =SUM('Historical Statement'!K135,'Historical Statement'!K136,'Historical Statement'!K138,'Historical Statement'!K139) -> -14.56 | N95: =SUM('Historical Statement'!L135,'Historical Statement'!L136,'Historical Statement'!L138,'Historical Statement'!L139) -> -137.33 | O95: =SUM('Historical Statement'!M135,'Historical Statement'!M136,'Historical Statement'!M138,'Historical Statement'!M139) -> -77.23 | Q95: =(P33-Q33)+Q45-P45 -> 0 | R95: =(Q33-R33)+R45-Q45 -> 0 | S95: =(R33-S33)+S45-R45 -> 0 | T95: =(S33-T33)+T45-S45 -> 0
D96: Total | J96: =SUM(J92:J95) -> -57.99 | K96: =SUM(K92:K95) -> 388.36 | L96: =SUM(L92:L95) -> -96.78 | M96: =SUM(M92:M95) -> -160.07 | N96: =SUM(N92:N95) -> 101.14 | O96: =SUM(O92:O95) -> -10.97 | P96: =SUM(P92:P95) -> -297.59722 | Q96: =SUM(Q92:Q95) -> -50.178375 | ... T96: =SUM(T92:T95) -> -50.827325
C98: Depriciation Schedule
D99: PPE opening | K99: =J102 -> 2063.28 | L99: =K102 -> 2054.21 | M99: =L102 -> 2224.25 | N99: =M102 -> 3348.53 | O99: =N102 -> 3642.11 | P99: =O102 -> 3753.59 | Q99: =P102 -> 3538.8935 | R99: =Q102 -> 3327.0861 | ... T99: =S102 -> 2926.0754
D100: Plus: Capex | K100: =K102-K99-K101 -> 231.06 | L100: =L102-L99-L101 -> 422.93 | M100: =M102-M99-M101 -> 1435.24 | N100: =N102-N99-N101 -> 692.79 | O100: =O102-O99-O101 -> 557.08 | P100: =(P10-O10)/P149 -> 251.39526 | Q100: =(Q10-P10)/Q149 -> 227.62515 | R100: =(R10-Q10)/R149 -> 208.11946 | S100: =(S10-R10)/S149 -> 191.67662 | T100: =(T10-S10)/T149 -> 177.5117
D101: Less: Depriciation | J101: =-J64 -> -220.45 | K101: =-K64 -> -240.13 | L101: =-L64 -> -252.89 | M101: =-M64 -> -310.96 | N101: =-N64 -> -399.21 | O101: =-O64 -> -445.6 | P101: =-P99*P126 -> -466.09181 | Q101: =-Q99*Q126 -> -439.43245 | R101: =-R99*R126 -> -413.13186 | S101: =-S99*S126 -> -387.675 | T101: =-T99*T126 -> -363.33744
D102: PPE Closing | J102: =J36 -> 2063.28 | K102: =K36 -> 2054.21 | L102: =L36 -> 2224.25 | M102: =M36 -> 3348.53 | N102: =N36 -> 3642.11 | O102: =O36 -> 3753.59 | P102: =SUM(P99:P101) -> 3538.8935 | Q102: =SUM(Q99:Q101) -> 3327.0861 | R102: =SUM(R99:R101) -> 3122.0738 | S102: =SUM(S99:S101) -> 2926.0754 | T102: =SUM(T99:T101) -> 2740.2496
C104: Debt & Interest Schedule
D105: Debt Opening | K105: =J107 -> 467.13 | L105: =K107 -> 509.06 | M105: =L107 -> 1030.1 | N105: =M107 -> 1173.79 | O105: =N107 -> 1365.09 | P105: =O107 -> 878.07 | Q105: =P107 -> 878.07 | R105: =Q107 -> 878.07 | ... T105: =S107 -> 878.07
D106: Issuance(Repayment) | K106: =K107-K105 -> 41.93 | L106: =L107-L105 -> 521.04 | M106: =M107-M105 -> 143.69 | N106: =N107-N105 -> 191.3 | O106: =O107-O105 -> -487.02 | P106: 0 | Q106: =P106 -> 0 | R106: =Q106 -> 0 | S106: =R106 -> 0 | T106: =S106 -> 0
D107: Debt Closing | J107: =J47 -> 467.13 | K107: =K47 -> 509.06 | L107: =L47 -> 1030.1 | M107: =M47 -> 1173.79 | N107: =N47 -> 1365.09 | O107: =O47 -> 878.07 | P107: =SUM(P105:P106) -> 878.07 | Q107: =SUM(Q105:Q106) -> 878.07 | R107: =SUM(R105:R106) -> 878.07 | S107: =SUM(S105:S106) -> 878.07 | T107: =SUM(T105:T106) -> 878.07
D108: Interest Expense | J108: =J19 -> -49.54 | K108: =K19 -> -30.81 | L108: =L19 -> -38.6 | M108: =M19 -> -78.24 | N108: =N19 -> -124.18 | O108: =O19 -> -163.5 | P108: =-P107*P129 -> -109.03195 | Q108: =-Q107*Q129 -> -109.03195 | R108: =-R107*R129 -> -109.03195 | S108: =-S107*S129 -> -109.03195 | T108: =-T107*T129 -> -109.03195
A111: Ratio Analysis & Assumptions
D113: Live Scenario | I113: Base Case | J113: =IF(I113=Scenarios!B8,1,IF('Full 3 FS Model & DCF'!I113=Scenarios!B9,2,3)) -> 1
I114: Units
D115: Revenue Growth | I115: % | K115: =K10/J10-1 -> 0.098586905 | L115: =L10/K10-1 -> 0.13878672 | M115: =M10/L10-1 -> 0.058887762 | N115: =N10/M10-1 -> 0.075813386 | O115: =O10/N10-1 -> 0.012824885 | P115: {=CHOOSE(J113,Scenarios!G8:K8,Scenarios!G9:K9,Scenarios!G10:K10)} -> 0.076979931 | Q115: 0.073130934 | R115: 0.069474387 | S115: 0.066000668 | T115: 0.062700635
I116: Base Case | J116: =IF(I116=Scenarios!B16,1,IF('Full 3 FS Model & DCF'!I116=Scenarios!B17,2,3)) -> 1
D118: COGS (% of Revenue) | I118: % | J118: =-J11/J10 -> 0.50097029 | K118: =-K11/K10 -> 0.50085079 | L118: =-L11/L10 -> 0.51794065 | M118: =-M11/M10 -> 0.54368862 | N118: =-N11/N10 -> 0.51974805 | O118: =-O11/O10 -> 0.52016343 | P118: {=CHOOSE(J116,Scenarios!G16:K16,Scenarios!G17:K17,Scenarios!G18:K18)} -> 0.51722697 | Q118: 0.51722697 | R118: 0.51722697 | S118: 0.51722697 | T118: 0.51722697
I119: Base Case | J119: =IF(I119=Scenarios!B22,1,IF('Full 3 FS Model & DCF'!I119=Scenarios!B23,2,3)) -> 1
D120: Salaries and Benefit expenses (% of Revenue) | I120: % | J120: =-J14/J10 -> 0.1088907 | K120: =-K14/K10 -> 0.10808386 | L120: =-L14/L10 -> 0.099180984 | M120: =-M14/M10 -> 0.098613257 | N120: =-N14/N10 -> 0.099932199 | O120: =-O14/O10 -> 0.10277965 | P120: {=CHOOSE(J119,Scenarios!G22:K22,Scenarios!G23:K23,Scenarios!G24:K24)} -> 0.10291344 | Q120: 0.10291344 | R120: 0.10291344 | S120: 0.10291344 | T120: 0.10291344
I122: Base Case | J122: =IF(I122=Scenarios!B28,1,IF('Full 3 FS Model & DCF'!I122=Scenarios!B29,2,3)) -> 1
D123: Other Expenses (% OF Revenue) | I123: % | J123: =-J15/J10 -> 0.18420675 | K123: =-K15/K10 -> 0.18161614 | L123: =-L15/L10 -> 0.17589184 | M123: =-M15/M10 -> 0.17000162 | N123: =-N15/N10 -> 0.18681539 | O123: =-O15/O10 -> 0.1926803 | P123: {=CHOOSE(J122,Scenarios!G28:K28,Scenarios!G29:K29,Scenarios!G30:K30)} -> 0.18186868 | Q123: 0.18186868 | R123: 0.18186868 | S123: 0.18186868 | T123: 0.18186868
I125: Base Case | J125: =IF(I125=Scenarios!B34,1,IF('Full 3 FS Model & DCF'!I125=Scenarios!B35,2,30)) -> 1
...

Sheet Other Key Financial Ratio
B1: Dabur India Ltd. | I1: Historical Period
B4: Key Financial Ratios | I4: 2020 | J4: =I4+1 -> 2021 | K4: =J4+1 -> 2022 | L4: =K4+1 -> 2023 | M4: =L4+1 -> 2024 | N4: =M4+1 -> 2025 | O4: Trends
B6: Profitability Ratio
B7: Operating Profit Margin | I7: ='Full 3 FS Model & DCF'!J16/'Full 3 FS Model & DCF'!J10 -> 0.20593226 | J7: ='Full 3 FS Model & DCF'!K16/'Full 3 FS Model & DCF'!K10 -> 0.20944921 | K7: ='Full 3 FS Model & DCF'!L16/'Full 3 FS Model & DCF'!L10 -> 0.20698652 | L7: ='Full 3 FS Model & DCF'!M16/'Full 3 FS Model & DCF'!M10 -> 0.1876965 | M7: ='Full 3 FS Model & DCF'!N16/'Full 3 FS Model & DCF'!N10 -> 0.19350436 | N7: ='Full 3 FS Model & DCF'!O16/'Full 3 FS Model & DCF'!O10 -> 0.18437661
B8: Net Profit Margin | I8: ='Full 3 FS Model & DCF'!J23/'Full 3 FS Model & DCF'!J10 -> 0.16636009 | J8: ='Full 3 FS Model & DCF'!K23/'Full 3 FS Model & DCF'!K10 -> 0.17737106 | K8: ='Full 3 FS Model & DCF'!L23/'Full 3 FS Model & DCF'!L10 -> 0.16017552 | L8: ='Full 3 FS Model & DCF'!M23/'Full 3 FS Model & DCF'!M10 -> 0.14769959 | M8: ='Full 3 FS Model & DCF'!N23/'Full 3 FS Model & DCF'!N10 -> 0.14606728 | N8: ='Full 3 FS Model & DCF'!O23/'Full 3 FS Model & DCF'!O10 -> 0.13849061
B10: Return Ratios
B11: ROA | I11: ='Full 3 FS Model & DCF'!J23/'Full 3 FS Model & DCF'!J40 -> 0.15479244 | J11: ='Full 3 FS Model & DCF'!K23/'Full 3 FS Model & DCF'!K40 -> 0.15635103 | K11: ='Full 3 FS Model & DCF'!L23/'Full 3 FS Model & DCF'!L40 -> 0.14197531 | L11: ='Full 3 FS Model & DCF'!M23/'Full 3 FS Model & DCF'!M40 -> 0.12471905 | M11: ='Full 3 FS Model & DCF'!N23/'Full 3 FS Model & DCF'!N40 -> 0.11980813 | N11: ='Full 3 FS Model & DCF'!O23/'Full 3 FS Model & DCF'!O40 -> 0.10766536
B12: ROE | I12: ='Full 3 FS Model & DCF'!J23/'Full 3 FS Model & DCF'!J54 -> 0.21919237 | J12: ='Full 3 FS Model & DCF'!K23/'Full 3 FS Model & DCF'!K54 -> 0.22130272 | K12: ='Full 3 FS Model & DCF'!L23/'Full 3 FS Model & DCF'!L54 -> 0.20809421 | L12: ='Full 3 FS Model & DCF'!M23/'Full 3 FS Model & DCF'!M54 -> 0.18978164 | M12: ='Full 3 FS Model & DCF'!N23/'Full 3 FS Model & DCF'!N54 -> 0.18363723 | N12: ='Full 3 FS Model & DCF'!O23/'Full 3 FS Model & DCF'!O54 -> 0.16108878
B13: ROCE | I13: ='Full 3 FS Model & DCF'!J18/('Full 3 FS Model & DCF'!J54+SUM('Full 3 FS Model & DCF'!J47:J48)) -> 0.21960321 | J13: ='Full 3 FS Model & DCF'!K18/('Full 3 FS Model & DCF'!K54+SUM('Full 3 FS Model & DCF'!K47:K48)) -> 0.21361187 | K13: ='Full 3 FS Model & DCF'!L18/('Full 3 FS Model & DCF'!L54+SUM('Full 3 FS Model & DCF'!L47:L48)) -> 0.20926623 | L13: ='Full 3 FS Model & DCF'!M18/('Full 3 FS Model & DCF'!M54+SUM('Full 3 FS Model & DCF'!M47:M48)) -> 0.17978998 | M13: ='Full 3 FS Model & DCF'!N18/('Full 3 FS Model & DCF'!N54+SUM('Full 3 FS Model & DCF'!N47:N48)) -> 0.17530786 | N13: ='Full 3 FS Model & DCF'!O18/('Full 3 FS Model & DCF'!O54+SUM('Full 3 FS Model & DCF'!O47:O48)) -> 0.15725275
B15: Liquidity Ratios
B16: Current ratio | I16: =('Full 3 FS Model & DCF'!J29+'Full 3 FS Model & DCF'!J30+'Full 3 FS Model & DCF'!J31+'Full 3 FS Model & DCF'!J32+'Full 3 FS Model & DCF'!J33)/('Full 3 FS Model & DCF'!J44+'Full 3 FS Model & DCF'!J45) -> 1.6082634 | J16: =('Full 3 FS Model & DCF'!K29+'Full 3 FS Model & DCF'!K30+'Full 3 FS Model & DCF'!K31+'Full 3 FS Model & DCF'!K32+'Full 3 FS Model & DCF'!K33)/('Full 3 FS Model & DCF'!K44+'Full 3 FS Model & DCF'!K45) -> 1.5677383 | K16: =('Full 3 FS Model & DCF'!L29+'Full 3 FS Model & DCF'!L30+'Full 3 FS Model & DCF'!L31+'Full 3 FS Model & DCF'!L32+'Full 3 FS Model & DCF'!L33)/('Full 3 FS Model & DCF'!L44+'Full 3 FS Model & DCF'!L45) -> 1.2771382 | L16: =('Full 3 FS Model & DCF'!M29+'Full 3 FS Model & DCF'!M30+'Full 3 FS Model & DCF'!M31+'Full 3 FS Model & DCF'!M32+'Full 3 FS Model & DCF'!M33)/('Full 3 FS Model & DCF'!M44+'Full 3 FS Model & DCF'!M45) -> 1.2100429 | M16: =('Full 3 FS Model & DCF'!N29+'Full 3 FS Model & DCF'!N30+'Full 3 FS Model & DCF'!N31+'Full 3 FS Model & DCF'!N32+'Full 3 FS Model & DCF'!N33)/('Full 3 FS Model & DCF'!N44+'Full 3 FS Model & DCF'!N45) -> 1.2136368 | N16: =('Full 3 FS Model & DCF'!O29+'Full 3 FS Model & DCF'!O30+'Full 3 FS Model & DCF'!O31+'Full 3 FS Model & DCF'!O32+'Full 3 FS Model & DCF'!O33)/('Full 3 FS Model & DCF'!O44+'Full 3 FS Model & DCF'!O45) -> 1.1231364
B17: Quick Ratio | I17: =('Full 3 FS Model & DCF'!J29+'Full 3 FS Model & DCF'!J30+'Full 3 FS Model & DCF'!J31+'Full 3 FS Model & DCF'!J33)/('Full 3 FS Model & DCF'!J44+'Full 3 FS Model & DCF'!J45) -> 0.96946713 | J17: =('Full 3 FS Model & DCF'!K29+'Full 3 FS Model & DCF'!K30+'Full 3 FS Model & DCF'!K31+'Full 3 FS Model & DCF'!K33)/('Full 3 FS Model & DCF'!K44+'Full 3 FS Model & DCF'!K45) -> 0.89008932 | K17: =('Full 3 FS Model & DCF'!L29+'Full 3 FS Model & DCF'!L30+'Full 3 FS Model & DCF'!L31+'Full 3 FS Model & DCF'!L33)/('Full 3 FS Model & DCF'!L44+'Full 3 FS Model & DCF'!L45) -> 0.56457325 | L17: =('Full 3 FS Model & DCF'!M29+'Full 3 FS Model & DCF'!M30+'Full 3 FS Model & DCF'!M31+'Full 3 FS Model & DCF'!M33)/('Full 3 FS Model & DCF'!M44+'Full 3 FS Model & DCF'!M45) -> 0.50691251 | M17: =('Full 3 FS Model & DCF'!N29+'Full 3 FS Model & DCF'!N30+'Full 3 FS Model & DCF'!N31+'Full 3 FS Model & DCF'!N33)/('Full 3 FS Model & DCF'!N44+'Full 3 FS Model & DCF'!N45) -> 0.61852071 | N17: =('Full 3 FS Model & DCF'!O29+'Full 3 FS Model & DCF'!O30+'Full 3 FS Model & DCF'!O31+'Full 3 FS Model & DCF'!O33)/('Full 3 FS Model & DCF'!O44+'Full 3 FS Model & DCF'!O45) -> 0.52632835
B19: Turnover Ratios (In days)
B20: Recievables Turnover Ratio | I20: ='Full 3 FS Model & DCF'!J10/'Full 3 FS Model & DCF'!J31 -> 10.693816 | J20: ='Full 3 FS Model & DCF'!K10/'Full 3 FS Model & DCF'!K31 -> 17.026336 | K20: ='Full 3 FS Model & DCF'!L10/'Full 3 FS Model & DCF'!L31 -> 16.851629 | L20: ='Full 3 FS Model & DCF'!M10/'Full 3 FS Model & DCF'!M31 -> 13.584554 | M20: ='Full 3 FS Model & DCF'!N10/'Full 3 FS Model & DCF'!N31 -> 13.801863 | N20: ='Full 3 FS Model & DCF'!O10/'Full 3 FS Model & DCF'!O31 -> 14.139662
B21: Inventory Turnover Ratios | I21: ='Full 3 FS Model & DCF'!J10/'Full 3 FS Model & DCF'!J32 -> 6.3089151 | J21: ='Full 3 FS Model & DCF'!K10/'Full 3 FS Model & DCF'!K32 -> 5.5133254 | K21: ='Full 3 FS Model & DCF'!L10/'Full 3 FS Model & DCF'!L32 -> 5.6967934 | L21: ='Full 3 FS Model & DCF'!M10/'Full 3 FS Model & DCF'!M32 -> 5.6960231 | M21: ='Full 3 FS Model & DCF'!N10/'Full 3 FS Model & DCF'!N32 -> 6.3709302 | N21: ='Full 3 FS Model & DCF'!O10/'Full 3 FS Model & DCF'!O32 -> 5.4619518
B22: Payables Turnover Ratio | I22: ='Full 3 FS Model & DCF'!J10/'Full 3 FS Model & DCF'!J44 -> 5.8722734 | J22: ='Full 3 FS Model & DCF'!K10/'Full 3 FS Model & DCF'!K44 -> 4.9923509 | K22: ='Full 3 FS Model & DCF'!L10/'Full 3 FS Model & DCF'!L44 -> 5.3959117 | L22: ='Full 3 FS Model & DCF'!M10/'Full 3 FS Model & DCF'!M44 -> 5.2729522 | M22: ='Full 3 FS Model & DCF'!N10/'Full 3 FS Model & DCF'!N44 -> 5.1220047 | N22: ='Full 3 FS Model & DCF'!O10/'Full 3 FS Model & DCF'!O44 -> 4.4465763
B24: Du Pont Analysis
B25: ROE | I25: =I12 -> 0.21919237 | J25: =J12 -> 0.22130272 | K25: =K12 -> 0.20809421 | L25: =L12 -> 0.18978164 | M25: =M12 -> 0.18363723 | N25: =N12 -> 0.16108878
B26: NPM | I26: =I8 -> 0.16636009 | J26: =J8 -> 0.17737106 | K26: =K8 -> 0.16017552 | L26: =L8 -> 0.14769959 | M26: =M8 -> 0.14606728 | N26: =N8 -> 0.13849061
B27: Assets Turnover | I27: ='Full 3 FS Model & DCF'!J10/'Full 3 FS Model & DCF'!J40 -> 0.93046619 | J27: ='Full 3 FS Model & DCF'!K10/'Full 3 FS Model & DCF'!K40 -> 0.88149123 | K27: ='Full 3 FS Model & DCF'!L10/'Full 3 FS Model & DCF'!L40 -> 0.88637335 | L27: ='Full 3 FS Model & DCF'!M10/'Full 3 FS Model & DCF'!M40 -> 0.84441025 | M27: ='Full 3 FS Model & DCF'!N10/'Full 3 FS Model & DCF'!N40 -> 0.82022565 | N27: ='Full 3 FS Model & DCF'!O10/'Full 3 FS Model & DCF'!O40 -> 0.7774199
B28: Asset/Equity | I28: ='Full 3 FS Model & DCF'!J40/'Full 3 FS Model & DCF'!J54 -> 1.4160406 | J28: ='Full 3 FS Model & DCF'!K40/'Full 3 FS Model & DCF'!K54 -> 1.4154221 | K28: ='Full 3 FS Model & DCF'!L40/'Full 3 FS Model & DCF'!L54 -> 1.465707 | L28: ='Full 3 FS Model & DCF'!M40/'Full 3 FS Model & DCF'!M54 -> 1.5216733 | M28: ='Full 3 FS Model & DCF'!N40/'Full 3 FS Model & DCF'!N54 -> 1.532761 | N28: ='Full 3 FS Model & DCF'!O40/'Full 3 FS Model & DCF'!O54 -> 1.4961989
B30: Cash Conversion Cycle
B31: Recievables Days | I31: =365/I20 -> 34.131875 | J31: =365/J20 -> 21.437377 | K31: =365/K20 -> 21.659627 | L31: =365/L20 -> 26.868752 | M31: =365/M20 -> 26.445706 | N31: =365/N20 -> 25.813912
B32: Inventory Days | I32: =365/I21 -> 57.854638 | J32: =365/J21 -> 66.203239 | K32: =365/K21 -> 64.071132 | L32: =365/L21 -> 64.079796 | M32: =365/M21 -> 57.291477 | N32: =365/N21 -> 66.825928
B33: Payables Days | I33: =365/I22 -> 62.156507 | J33: =365/J22 -> 73.111848 | K33: =365/K22 -> 67.643805 | L33: =365/L22 -> 69.221185 | M33: =365/M22 -> 71.261161 | N33: =365/N22 -> 82.085625
B35: Cash Conversion Cycle | I35: =I31+I32-I33 -> 29.830007 | J35: =J31+J32-J33 -> 14.528769 | K35: =K31+K32-K33 -> 18.086954 | L35: =L31+L32-L33 -> 21.727363 | M35: =M31+M32-M33 -> 12.476022 | N35: =N31+N32-N33 -> 10.554215
B39: Back to cover

Sheet Comp- Valuation- Dabur
B1: Dabur India Ltd.
B4: Comparable Company Valuation
B6: (Amounts in crores)
D7: Market Data | K7: Financial Data | O7: Valuation
D8: Price | E8: No. of shares | F8: Market Cap | G8: Debt | H8: Cash and Equivalents | I8: EV | K8: Sales | L8: EBITDA | M8: Earnings | O8: EV/Sales | P8: EV/EBITDA | Q8: P/E
B9: Company Name | D9: (₹ Share) | E9: (in crore) | F9: (in crore) | G9: (in crore) | H9: (in crore) | I9: (in crore) | K9: (in crore) | L9: (in crore) | M9: (in crore) | O9: x | P9: x | Q9: x
B10: ='Comp value data'!B5 -> Dabur India | D10: ='Comp value data'!C5 -> 518.65 | E10: ='Comp value data'!D5 -> 177.37 | F10: =D10*E10 -> 91992.95 | G10: ='Comp value data'!F5 -> 950.37 | H10: ='Comp value data'!G5 -> 578.01 | I10: =F10+G10-H10 -> 92365.31 | K10: ='Comp value data'!H5 -> 12781.29 | L10: ='Comp value data'!I5 -> 2917.94 | M10: ='Comp value data'!J5 -> 1808.97 | O10: =I10/K10 -> 7.2266031 | P10: =I10/L10 -> 31.654287 | Q10: =F10/M10 -> 50.853773
B11: ='Comp value data'!B6 -> Godrej Consumer | D11: ='Comp value data'!C6 -> 1121.8 | E11: ='Comp value data'!D6 -> 102.31 | F11: =D11*E11 -> 114771.36 | G11: ='Comp value data'!F6 -> 4113.49 | H11: ='Comp value data'!G6 -> 1080.34 | I11: =F11+G11-H11 -> 117804.51 | K11: ='Comp value data'!H6 -> 14853.33 | L11: ='Comp value data'!I6 -> 3247.18 | M11: ='Comp value data'!J6 -> 1882.61 | O11: =I11/K11 -> 7.931185 | P11: =I11/L11 -> 36.27902 | Q11: =F11/M11 -> 60.963959
B12: ='Comp value data'!B7 -> Colgate-Palmoliv | D12: ='Comp value data'!C7 -> 2167.2 | E12: ='Comp value data'!D7 -> 27.2 | F12: =D12*E12 -> 58947.84 | G12: ='Comp value data'!F7 -> 59.99 | H12: ='Comp value data'!G7 -> 1347.47 | I12: =F12+G12-H12 -> 57660.36 | K12: ='Comp value data'!H7 -> 5877.91 | L12: ='Comp value data'!I7 -> 1942.8 | M12: ='Comp value data'!J7 -> 1325.91 | O12: =I12/K12 -> 9.8096704 | P12: =I12/L12 -> 29.678999 | Q12: =F12/M12 -> 44.458402
B13: ='Comp value data'!B8 -> P & G Hygiene | D13: ='Comp value data'!C8 -> 13174 | E13: ='Comp value data'!D8 -> 3.25 | F13: =D13*E13 -> 42815.5 | G13: ='Comp value data'!F8 -> 2.06 | H13: ='Comp value data'!G8 -> 793.12 | I13: =F13+G13-H13 -> 42024.44 | K13: ='Comp value data'!H8 -> 4326.46 | L13: ='Comp value data'!I8 -> 1177.94 | M13: ='Comp value data'!J8 -> 826.61 | O13: =I13/K13 -> 9.7133546 | P13: =I13/L13 -> 35.676214 | Q13: =F13/M13 -> 51.796494
B14: ='Comp value data'!B9 -> Gillette India | D14: ='Comp value data'!C9 -> 8480.5 | E14: ='Comp value data'!D9 -> 3.26 | F14: =D14*E14 -> 27646.43 | G14: ='Comp value data'!F9 -> 0.05 | H14: ='Comp value data'!G9 -> 591.52 | I14: =F14+G14-H14 -> 27054.96 | K14: ='Comp value data'!H9 -> 2970.55 | L14: ='Comp value data'!I9 -> 862.8 | M14: ='Comp value data'!J9 -> 573.99 | O14: =I14/K14 -> 9.1077275 | P14: =I14/L14 -> 31.357163 | Q14: =F14/M14 -> 48.165351
B15: ='Comp value data'!B10 -> Emami | D15: ='Comp value data'!C10 -> 514.1 | E15: ='Comp value data'!D10 -> 43.65 | F15: =D15*E15 -> 22440.465 | G15: ='Comp value data'!F10 -> 89.79 | H15: ='Comp value data'!G10 -> 272.9 | I15: =F15+G15-H15 -> 22257.355 | K15: ='Comp value data'!H10 -> 3807.21 | L15: ='Comp value data'!I10 -> 1090.24 | M15: ='Comp value data'!J10 -> 818.08 | O15: =I15/K15 -> 5.8461065 | P15: =I15/L15 -> 20.415097 | Q15: =F15/M15 -> 27.430649
B16: ='Comp value data'!B11 -> Honasa Consumer | D16: ='Comp value data'!C11 -> 273.95 | E16: ='Comp value data'!D11 -> 32.54 | F16: =D16*E16 -> 8914.333 | G16: ='Comp value data'!F11 -> 109.79 | H16: ='Comp value data'!G11 -> 294.99 | I16: =F16+G16-H16 -> 8729.133 | K16: ='Comp value data'!H11 -> 1994.23 | L16: ='Comp value data'!I11 -> 141.55 | M16: ='Comp value data'!J11 -> 71.17 | O16: =I16/K16 -> 4.3771947 | P16: =I16/L16 -> 61.668195 | Q16: =F16/M16 -> 125.25408
B18: Average | O18: =AVERAGE(O10:O16) -> 7.7159774 | P18: =AVERAGE(P10:P16) -> 35.246996 | Q18: =AVERAGE(Q10:Q16) -> 58.41753
B19: Median | O19: =MEDIAN(O10:O16) -> 7.931185 | P19: =MEDIAN(P10:P16) -> 31.654287 | Q19: =MEDIAN(Q10:Q16) -> 50.853773
B22: Metric | E22: Comps | F22: EV | H22: Net Debt | I22: Equity Value | K22: Shares | L22: Share Price
B23: EV/Revenue | E23: =O18 -> 7.7159774 | F23: =E23*K10 -> 98620.145 | H23: =G10-H10 -> 372.36 | I23: =F23-H23 -> 98247.785 | K23: =E10 -> 177.37 | L23: =I23/K23 -> 553.91433
B24: EV/EBITDA | E24: =P18 -> 35.246996 | F24: =E24*L10 -> 102848.62 | H24: =G10-H10 -> 372.36 | I24: =F24-H24 -> 102476.26 | K24: =E10 -> 177.37 | L24: =I24/K24 -> 577.75419
B25: P/E | E25: =Q18 -> 58.41753 | F25: =I25+H25 -> 106047.92 | H25: =G10-H10 -> 372.36 | I25: =E25*M10 -> 105675.56 | K25: =E10 -> 177.37 | L25: =I25/K25 -> 595.79162
B28: Back to cover

Sheet Scenarios
B1: Dabur India Ltd.
B4: Scenarios
B6: Revenue Growth
B7: Scenarios | D7: Growth(%) | G7: 2026 | H7: =G7+1 -> 2027 | I7: =H7+1 -> 2028 | J7: =I7+1 -> 2029 | K7: =J7+1 -> 2030 | L7: Long Term Growth
B8: Base Case | D8: =AVERAGE('Full 3 FS Model & DCF'!K115:O115) -> 0.076979931 | G8: =D8 -> 0.076979931 | H8: =G8*(1-$D$11) -> 0.073130934 | I8: =H8*(1-$D$11) -> 0.069474387 | J8: =I8*(1-$D$11) -> 0.066000668 | K8: =J8*(1-$D$11) -> 0.062700635 | L8: 0.06
B9: Best Case | D9: =MAX('Full 3 FS Model & DCF'!K115:O115) -> 0.13878672 | G9: =D9 -> 0.13878672 | H9: =G9*(1-$D$11) -> 0.13184738 | I9: =H9*(1-$D$11) -> 0.12525501 | J9: =I9*(1-$D$11) -> 0.11899226 | K9: =J9*(1-$D$11) -> 0.11304265
B10: Worst Case | D10: =MIN('Full 3 FS Model & DCF'!K115:O115) -> 0.012824885 | G10: =D10 -> 0.012824885 | H10: =G10*(1-$D$11) -> 0.012183641 | I10: =H10*(1-$D$11) -> 0.011574459 | J10: =I10*(1-$D$11) -> 0.010995736 | K10: =J10*(1-$D$11) -> 0.010445949
B11: Annual Growth Tapering | D11: 0.05
B14: COGS (% of Revenue)
B15: Scenarios | D15: Growth(%) | G15: 2026 | H15: =G15+1 -> 2027 | I15: =H15+1 -> 2028 | J15: =I15+1 -> 2029 | K15: =J15+1 -> 2030
B16: Base Case | D16: =AVERAGE('Full 3 FS Model & DCF'!J118:O118) -> 0.51722697 | G16: =D16 -> 0.51722697 | H16: =G16 -> 0.51722697 | I16: =H16 -> 0.51722697 | J16: =I16 -> 0.51722697 | K16: =J16 -> 0.51722697
B17: Best Case | D17: =MIN('Full 3 FS Model & DCF'!J118:O118) -> 0.50085079 | G17: =D17 -> 0.50085079 | H17: =G17 -> 0.50085079 | I17: =H17 -> 0.50085079 | J17: =I17 -> 0.50085079 | K17: =J17 -> 0.50085079
B18: Worst Case | D18: =MAX('Full 3 FS Model & DCF'!J118:O118) -> 0.54368862 | G18: =D18 -> 0.54368862 | H18: =G18 -> 0.54368862 | I18: =H18 -> 0.54368862 | J18: =I18 -> 0.54368862 | K18: =J18 -> 0.54368862
B20: Salary & Benefit Expenses (% of Revenue)
B21: Scenarios | D21: Growth(%) | G21: 2026 | H21: =G21+1 -> 2027 | I21: =H21+1 -> 2028 | J21: =I21+1 -> 2029 | K21: =J21+1 -> 2030
B22: Base Case | D22: =AVERAGE('Full 3 FS Model & DCF'!J120:O120) -> 0.10291344 | G22: =D22 -> 0.10291344 | H22: =G22 -> 0.10291344 | I22: =H22 -> 0.10291344 | J22: =I22 -> 0.10291344 | K22: =J22 -> 0.10291344
B23: Best Case | D23: =MIN('Full 3 FS Model & DCF'!J120:O120) -> 0.098613257 | G23: =D23 -> 0.098613257 | H23: =G23 -> 0.098613257 | I23: =H23 -> 0.098613257 | J23: =I23 -> 0.098613257 | K23: =J23 -> 0.098613257
B24: Worst Case | D24: =MAX('Full 3 FS Model & DCF'!J120:O120) -> 0.1088907 | G24: =D24 -> 0.1088907 | H24: =G24 -> 0.1088907 | I24: =H24 -> 0.1088907 | J24: =I24 -> 0.1088907 | K24: =J24 -> 0.1088907
B26: Other Expenses (% of Revenue)
B27: Scenarios | D27: Growth(%) | G27: 2026 | H27: =G27+1 -> 2027 | I27: =H27+1 -> 2028 | J27: =I27+1 -> 2029 | K27: =J27+1 -> 2030
B28: Base Case | D28: =AVERAGE('Full 3 FS Model & DCF'!J123:O123) -> 0.18186868 | G28: =D28 -> 0.18186868 | H28: =G28 -> 0.18186868 | I28: =H28 -> 0.18186868 | J28: =I28 -> 0.18186868 | K28: =J28 -> 0.18186868
B29: Best Case | D29: =MIN('Full 3 FS Model & DCF'!J123:O123) -> 0.17000162 | G29: =D29 -> 0.17000162 | H29: =G29 -> 0.17000162 | I29: =H29 -> 0.17000162 | J29: =I29 -> 0.17000162 | K29: =J29 -> 0.17000162
B30: Worst Case | D30: =MAX('Full 3 FS Model & DCF'!J123:O123) -> 0.1926803 | G30: =D30 -> 0.1926803 | H30: =G30 -> 0.1926803 | I30: =H30 -> 0.1926803 | J30: =I30 -> 0.1926803 | K30: =J30 -> 0.1926803
B32: D&A Expenses(% of PPE)
B33: Scenarios | D33: Growth(%) | G33: 2026 | H33: =G33+1 -> 2027 | I33: =H33+1 -> 2028 | J33: =I33+1 -> 2029 | K33: =J33+1 -> 2030
B34: Base Case | D34: =AVERAGE('Full 3 FS Model & DCF'!K126:O126) -> 0.12417227 | G34: =D34 -> 0.12417227 | H34: =G34 -> 0.12417227 | I34: =H34 -> 0.12417227 | J34: =I34 -> 0.12417227 | K34: =J34 -> 0.12417227
B35: Best Case | D35: =MIN('Full 3 FS Model & DCF'!K126:O126) -> 0.11638265 | G35: =D35 -> 0.11638265 | H35: =G35 -> 0.11638265 | I35: =H35 -> 0.11638265 | J35: =I35 -> 0.11638265 | K35: =J35 -> 0.11638265
B36: Worst Case | D36: =MAX('Full 3 FS Model & DCF'!K126:O126) -> 0.13980443 | G36: =D36 -> 0.13980443 | H36: =G36 -> 0.13980443 | I36: =H36 -> 0.13980443 | J36: =I36 -> 0.13980443 | K36: =J36 -> 0.13980443
B38: Interest (% of Debt)
B39: Scenarios | D39: Growth(%) | G39: 2026 | H39: =G39+1 -> 2027 | I39: =H39+1 -> 2028 | J39: =I39+1 -> 2029 | K39: =J39+1 -> 2030
B40: Base Case | D40: =AVERAGE('Full 3 FS Model & DCF'!K129:O129) -> 0.088660428 | G40: =D40 -> 0.088660428 | H40: =G40 -> 0.088660428 | I40: =H40 -> 0.088660428 | J40: =I40 -> 0.088660428 | K40: =J40 -> 0.088660428
B41: Best Case | D41: =MIN('Full 3 FS Model & DCF'!K129:O129) -> 0.065955944 | G41: =D41 -> 0.065955944 | H41: =G41 -> 0.065955944 | I41: =H41 -> 0.065955944 | J41: =I41 -> 0.065955944 | K41: =J41 -> 0.065955944
B42: Worst Case | D42: =MAX('Full 3 FS Model & DCF'!K129:O129) -> 0.11977232 | G42: =D42 -> 0.11977232 | H42: =G42 -> 0.11977232 | I42: =H42 -> 0.11977232 | J42: =I42 -> 0.11977232 | K42: =J42 -> 0.11977232
B44: Other Income (Expenses)(% of Revenue)
B45: Scenarios | D45: Growth(%) | G45: 2026 | H45: =G45+1 -> 2027 | I45: =H45+1 -> 2028 | J45: =I45+1 -> 2029 | K45: =J45+1 -> 2030
B46: Base Case | D46: =AVERAGE('Full 3 FS Model & DCF'!J132:O132) -> 0.034535944 | G46: =D46 -> 0.034535944 | H46: =G46 -> 0.034535944 | I46: =H46 -> 0.034535944 | J46: =I46 -> 0.034535944 | K46: =J46 -> 0.034535944
B47: Best Case | D47: =MAX('Full 3 FS Model & DCF'!J132:O132) -> 0.043786998 | G47: =D47 -> 0.043786998 | H47: =G47 -> 0.043786998 | I47: =H47 -> 0.043786998 | J47: =I47 -> 0.043786998 | K47: =J47 -> 0.043786998
B48: Worst Case | D48: =MIN('Full 3 FS Model & DCF'!J132:O132) -> 0.023586819 | G48: =D48 -> 0.023586819 | H48: =G48 -> 0.023586819 | I48: =H48 -> 0.023586819 | J48: =I48 -> 0.023586819 | K48: =J48 -> 0.023586819
B50: Tax Rate (% of EBT)
B51: Scenarios | D51: Growth(%) | G51: 2026 | H51: =G51+1 -> 2027 | I51: =H51+1 -> 2028 | J51: =I51+1 -> 2029 | K51: =J51+1 -> 2030
B52: Base Case | D52: =AVERAGE('Full 3 FS Model & DCF'!J135:O135) -> 0.21059274 | G52: =D52 -> 0.21059274 | H52: =G52 -> 0.21059274 | I52: =H52 -> 0.21059274 | J52: =I52 -> 0.21059274 | K52: =J52 -> 0.21059274
B53: Best Case | D53: =MIN('Full 3 FS Model & DCF'!J135:O135) -> 0.16190779 | G53: =D53 -> 0.16190779 | H53: =G53 -> 0.16190779 | I53: =H53 -> 0.16190779 | J53: =I53 -> 0.16190779 | K53: =J53 -> 0.16190779
B54: Worst Case | D54: =MAX('Full 3 FS Model & DCF'!J135:O135) -> 0.233008 | G54: =D54 -> 0.233008 | H54: =G54 -> 0.233008 | I54: =H54 -> 0.233008 | J54: =I54 -> 0.233008 | K54: =J54 -> 0.233008
B56: Dividend Payout
B57: Scenarios | D57: Growth(%) | G57: 2026 | H57: =G57+1 -> 2027 | I57: =H57+1 -> 2028 | J57: =I57+1 -> 2029 | K57: =J57+1 -> 2030
B58: Base Case | D58: =AVERAGE('Full 3 FS Model & DCF'!J138:O138) -> 0.48247105 | G58: =D58 -> 0.48247105 | H58: =G58 -> 0.48247105 | I58: =H58 -> 0.48247105 | J58: =I58 -> 0.48247105 | K58: =J58 -> 0.48247105
B59: Best Case | D59: =MIN('Full 3 FS Model & DCF'!J138:O138) -> 0.3491179 | G59: =D59 -> 0.3491179 | H59: =G59 -> 0.3491179 | I59: =H59 -> 0.3491179 | J59: =I59 -> 0.3491179 | K59: =J59 -> 0.3491179
B60: Worst Case | D60: =MAX('Full 3 FS Model & DCF'!J138:O138) -> 0.56026025 | G60: =D60 -> 0.56026025 | H60: =G60 -> 0.56026025 | I60: =H60 -> 0.56026025 | J60: =I60 -> 0.56026025 | K60: =J60 -> 0.56026025
B62: Account Receivable (Days)
B63: Scenarios | D63: Growth(%) | G63: 2026 | H63: =G63+1 -> 2027 | I63: =H63+1 -> 2028 | J63: =I63+1 -> 2029 | K63: =J63+1 -> 2030
B64: Base Case | D64: =AVERAGE('Full 3 FS Model & DCF'!J141:O141) -> 26.059542 | G64: =D64 -> 26.059542 | H64: =G64 -> 26.059542 | I64: =H64 -> 26.059542 | J64: =I64 -> 26.059542 | K64: =J64 -> 26.059542
B65: Best Case | D65: =MIN('Full 3 FS Model & DCF'!J141:O141) -> 21.437377 | G65: =D65 -> 21.437377 | H65: =G65 -> 21.437377 | I65: =H65 -> 21.437377 | J65: =I65 -> 21.437377 | K65: =J65 -> 21.437377
B66: Worst Case | D66: =MAX('Full 3 FS Model & DCF'!J141:O141) -> 34.131875 | G66: =D66 -> 34.131875 | H66: =G66 -> 34.131875 | I66: =H66 -> 34.131875 | J66: =I66 -> 34.131875 | K66: =J66 -> 34.131875
B68: Account Payable (Days)
B69: Scenarios | D69: Growth(%) | G69: 2026 | H69: =G69+1 -> 2027 | I69: =H69+1 -> 2028 | J69: =I69+1 -> 2029 | K69: =J69+1 -> 2030
B70: Base Case | D70: =AVERAGE('Full 3 FS Model & DCF'!J144:O144) -> 137.14687 | G70: =D70 -> 137.14687 | H70: =G70 -> 137.14687 | I70: =H70 -> 137.14687 | J70: =I70 -> 137.14687 | K70: =J70 -> 137.14687
B71: Best Case | D71: =MAX('Full 3 FS Model & DCF'!J144:O144) -> 157.80737 | G71: =D71 -> 157.80737 | H71: =G71 -> 157.80737 | I71: =H71 -> 157.80737 | J71: =I71 -> 157.80737 | K71: =J71 -> 157.80737
B72: Worst Case | D72: =MIN('Full 3 FS Model & DCF'!J144:O144) -> 124.07224 | G72: =D72 -> 124.07224 | H72: =G72 -> 124.07224 | I72: =H72 -> 124.07224 | J72: =I72 -> 124.07224 | K72: =J72 -> 124.07224
B74: Inventory (Days)
B75: Scenarios | D75: Growth(%) | G75: 2026 | H75: =G75+1 -> 2027 | I75: =H75+1 -> 2028 | J75: =I75+1 -> 2029 | K75: =J75+1 -> 2030
B76: Base Case | D76: =AVERAGE('Full 3 FS Model & DCF'!J147:O147) -> 121.32198 | G76: =D76 -> 121.32198 | H76: =G76 -> 121.32198 | I76: =G76 -> 121.32198 | J76: =H76 -> 121.32198 | K76: =I76 -> 121.32198
B77: Best Case | D77: =MIN('Full 3 FS Model & DCF'!J147:O147) -> 110.22933 | G77: =D77 -> 110.22933 | H77: =G77 -> 110.22933 | I77: =H77 -> 110.22933 | J77: =I77 -> 110.22933 | K77: =J77 -> 110.22933
B78: Worst Case | D78: =MAX('Full 3 FS Model & DCF'!J147:O147) -> 132.18156 | G78: =D78 -> 132.18156 | H78: =G78 -> 132.18156 | I78: =H78 -> 132.18156 | J78: =I78 -> 132.18156 | K78: =J78 -> 132.18156
B82: Back to cover

Sheet Common-Size Statement
A1: Dabur India Ltd.
A4: Common Size Statement
A6: Common Size Income Statement
A7: Particulars | E7: ='Other Key Financial Ratio'!I4 -> 2020 | F7: ='Other Key Financial Ratio'!J4 -> 2021 | G7: ='Other Key Financial Ratio'!K4 -> 2022 | H7: ='Other Key Financial Ratio'!L4 -> 2023 | I7: ='Other Key Financial Ratio'!M4 -> 2024 | J7: ='Other Key Financial Ratio'!N4 -> 2025 | K7: Trends
C9: Income
D10: Revenue | E10: ='Full 3 FS Model & DCF'!J10/'Full 3 FS Model & DCF'!J10 -> 1 | F10: ='Full 3 FS Model & DCF'!K10/'Full 3 FS Model & DCF'!K10 -> 1 | G10: ='Full 3 FS Model & DCF'!L10/'Full 3 FS Model & DCF'!L10 -> 1 | H10: ='Full 3 FS Model & DCF'!M10/'Full 3 FS Model & DCF'!M10 -> 1 | I10: ='Full 3 FS Model & DCF'!N10/'Full 3 FS Model & DCF'!N10 -> 1 | J10: ='Full 3 FS Model & DCF'!O10/'Full 3 FS Model & DCF'!O10 -> 1
D11: Cost of Good Sold | E11: =-'Full 3 FS Model & DCF'!J11/'Full 3 FS Model & DCF'!J10 -> 0.50097029 | F11: =-'Full 3 FS Model & DCF'!K11/'Full 3 FS Model & DCF'!K10 -> 0.50085079 | G11: =-'Full 3 FS Model & DCF'!L11/'Full 3 FS Model & DCF'!L10 -> 0.51794065 | H11: =-'Full 3 FS Model & DCF'!M11/'Full 3 FS Model & DCF'!M10 -> 0.54368862 | I11: =-'Full 3 FS Model & DCF'!N11/'Full 3 FS Model & DCF'!N10 -> 0.51974805 | J11: =-'Full 3 FS Model & DCF'!O11/'Full 3 FS Model & DCF'!O10 -> 0.52016343
D13: Gross Profit | E13: ='Full 3 FS Model & DCF'!J12/'Full 3 FS Model & DCF'!J10 -> 0.49902971 | F13: ='Full 3 FS Model & DCF'!K12/'Full 3 FS Model & DCF'!K10 -> 0.49914921 | G13: ='Full 3 FS Model & DCF'!L12/'Full 3 FS Model & DCF'!L10 -> 0.48205935 | H13: ='Full 3 FS Model & DCF'!M12/'Full 3 FS Model & DCF'!M10 -> 0.45631138 | I13: ='Full 3 FS Model & DCF'!N12/'Full 3 FS Model & DCF'!N10 -> 0.48025195 | J13: ='Full 3 FS Model & DCF'!O12/'Full 3 FS Model & DCF'!O10 -> 0.47983657
C15: Expenses
D16: Salaries and Benefit expenses | E16: =-'Full 3 FS Model & DCF'!J14/'Full 3 FS Model & DCF'!J10 -> 0.1088907 | F16: =-'Full 3 FS Model & DCF'!K14/'Full 3 FS Model & DCF'!K10 -> 0.10808386 | G16: =-'Full 3 FS Model & DCF'!L14/'Full 3 FS Model & DCF'!L10 -> 0.099180984 | H16: =-'Full 3 FS Model & DCF'!M14/'Full 3 FS Model & DCF'!M10 -> 0.098613257 | I16: =-'Full 3 FS Model & DCF'!N14/'Full 3 FS Model & DCF'!N10 -> 0.099932199 | J16: =-'Full 3 FS Model & DCF'!O14/'Full 3 FS Model & DCF'!O10 -> 0.10277965
D17: Other Expenses | E17: =-'Full 3 FS Model & DCF'!J15/'Full 3 FS Model & DCF'!J10 -> 0.18420675 | F17: =-'Full 3 FS Model & DCF'!K15/'Full 3 FS Model & DCF'!K10 -> 0.18161614 | G17: =-'Full 3 FS Model & DCF'!L15/'Full 3 FS Model & DCF'!L10 -> 0.17589184 | H17: =-'Full 3 FS Model & DCF'!M15/'Full 3 FS Model & DCF'!M10 -> 0.17000162 | I17: =-'Full 3 FS Model & DCF'!N15/'Full 3 FS Model & DCF'!N10 -> 0.18681539 | J17: =-'Full 3 FS Model & DCF'!O15/'Full 3 FS Model & DCF'!O10 -> 0.1926803
D19: EBITDA | E19: ='Full 3 FS Model & DCF'!J16/'Full 3 FS Model & DCF'!J10 -> 0.20593226 | F19: ='Full 3 FS Model & DCF'!K16/'Full 3 FS Model & DCF'!K10 -> 0.20944921 | G19: ='Full 3 FS Model & DCF'!L16/'Full 3 FS Model & DCF'!L10 -> 0.20698652 | H19: ='Full 3 FS Model & DCF'!M16/'Full 3 FS Model & DCF'!M10 -> 0.1876965 | I19: ='Full 3 FS Model & DCF'!N16/'Full 3 FS Model & DCF'!N10 -> 0.19350436 | J19: ='Full 3 FS Model & DCF'!O16/'Full 3 FS Model & DCF'!O10 -> 0.18437661
D20: Depreciation and amortisation expense | E20: =-'Full 3 FS Model & DCF'!J17/'Full 3 FS Model & DCF'!J10 -> 0.025328629 | F20: =-'Full 3 FS Model & DCF'!K17/'Full 3 FS Model & DCF'!K10 -> 0.025113866 | G20: =-'Full 3 FS Model & DCF'!L17/'Full 3 FS Model & DCF'!L10 -> 0.023225037 | H20: =-'Full 3 FS Model & DCF'!M17/'Full 3 FS Model & DCF'!M10 -> 0.026969902 | I20: =-'Full 3 FS Model & DCF'!N17/'Full 3 FS Model & DCF'!N10 -> 0.032183947 | J20: =-'Full 3 FS Model & DCF'!O17/'Full 3 FS Model & DCF'!O10 -> 0.035468981
D22: EBIT | E22: ='Full 3 FS Model & DCF'!J18/'Full 3 FS Model & DCF'!J10 -> 0.18060364 | F22: ='Full 3 FS Model & DCF'!K18/'Full 3 FS Model & DCF'!K10 -> 0.18433534 | G22: ='Full 3 FS Model & DCF'!L18/'Full 3 FS Model & DCF'!L10 -> 0.18376148 | H22: ='Full 3 FS Model & DCF'!M18/'Full 3 FS Model & DCF'!M10 -> 0.1607266 | I22: ='Full 3 FS Model & DCF'!N18/'Full 3 FS Model & DCF'!N10 -> 0.16132041 | J22: ='Full 3 FS Model & DCF'!O18/'Full 3 FS Model & DCF'!O10 -> 0.14890763
D23: Interest | E23: =-'Full 3 FS Model & DCF'!J19/'Full 3 FS Model & DCF'!J10 -> 0.0056919041 | F23: =-'Full 3 FS Model & DCF'!K19/'Full 3 FS Model & DCF'!K10 -> 0.0032222472 | G23: =-'Full 3 FS Model & DCF'!L19/'Full 3 FS Model & DCF'!L10 -> 0.003544966 | H23: =-'Full 3 FS Model & DCF'!M19/'Full 3 FS Model & DCF'!M10 -> 0.006785841 | I23: =-'Full 3 FS Model & DCF'!N19/'Full 3 FS Model & DCF'!N10 -> 0.010011279 | J23: =-'Full 3 FS Model & DCF'!O19/'Full 3 FS Model & DCF'!O10 -> 0.013014314
D24: Other Income (Expenses) | E24: ='Full 3 FS Model & DCF'!J20/'Full 3 FS Model & DCF'!J10 -> 0.023586819 | F24: ='Full 3 FS Model & DCF'!K20/'Full 3 FS Model & DCF'!K10 -> 0.034020279 | G24: ='Full 3 FS Model & DCF'!L20/'Full 3 FS Model & DCF'!L10 -> 0.028300951 | H24: ='Full 3 FS Model & DCF'!M20/'Full 3 FS Model & DCF'!M10 -> 0.038629163 | I24: ='Full 3 FS Model & DCF'!N20/'Full 3 FS Model & DCF'!N10 -> 0.038891455 | J24: ='Full 3 FS Model & DCF'!O20/'Full 3 FS Model & DCF'!O10 -> 0.043786998
D26: Earning Before Tax | E26: ='Full 3 FS Model & DCF'!J21/'Full 3 FS Model & DCF'!J10 -> 0.19849855 | F26: ='Full 3 FS Model & DCF'!K21/'Full 3 FS Model & DCF'!K10 -> 0.21513337 | G26: ='Full 3 FS Model & DCF'!L21/'Full 3 FS Model & DCF'!L10 -> 0.20851747 | H26: ='Full 3 FS Model & DCF'!M21/'Full 3 FS Model & DCF'!M10 -> 0.19256992 | I26: ='Full 3 FS Model & DCF'!N21/'Full 3 FS Model & DCF'!N10 -> 0.19020059 | J26: ='Full 3 FS Model & DCF'!O21/'Full 3 FS Model & DCF'!O10 -> 0.17968032
D27: Tax | E27: =-'Full 3 FS Model & DCF'!J22/'Full 3 FS Model & DCF'!J10 -> 0.032138462 | F27: =-'Full 3 FS Model & DCF'!K22/'Full 3 FS Model & DCF'!K10 -> 0.037762311 | G27: =-'Full 3 FS Model & DCF'!L22/'Full 3 FS Model & DCF'!L10 -> 0.048341948 | H27: =-'Full 3 FS Model & DCF'!M22/'Full 3 FS Model & DCF'!M10 -> 0.044870333 | I27: =-'Full 3 FS Model & DCF'!N22/'Full 3 FS Model & DCF'!N10 -> 0.044133309 | J27: =-'Full 3 FS Model & DCF'!O22/'Full 3 FS Model & DCF'!O10 -> 0.041189707
D29: Net Profit | E29: ='Full 3 FS Model & DCF'!J23/'Full 3 FS Model & DCF'!J10 -> 0.16636009 | F29: ='Full 3 FS Model & DCF'!K23/'Full 3 FS Model & DCF'!K10 -> 0.17737106 | G29: ='Full 3 FS Model & DCF'!L23/'Full 3 FS Model & DCF'!L10 -> 0.16017552 | H29: ='Full 3 FS Model & DCF'!M23/'Full 3 FS Model & DCF'!M10 -> 0.14769959 | I29: ='Full 3 FS Model & DCF'!N23/'Full 3 FS Model & DCF'!N10 -> 0.14606728 | J29: ='Full 3 FS Model & DCF'!O23/'Full 3 FS Model & DCF'!O10 -> 0.13849061
A32: Common Size Balancesheet
B34: Assets
C35: Current Assets:
D36: Cash | E36: ='Full 3 FS Model & DCF'!J29/'Full 3 FS Model & DCF'!$J$40 -> 0.017526173 | F36: ='Full 3 FS Model & DCF'!K29/'Full 3 FS Model & DCF'!$K$40 -> 0.022239062 | G36: ='Full 3 FS Model & DCF'!L29/'Full 3 FS Model & DCF'!$L$40 -> 0.020831892 | H36: ='Full 3 FS Model & DCF'!M29/'Full 3 FS Model & DCF'!$M$40 -> 0.010752602 | I36: ='Full 3 FS Model & DCF'!N29/'Full 3 FS Model & DCF'!$N$40 -> 0.016372759 | J36: ='Full 3 FS Model & DCF'!O29/'Full 3 FS Model & DCF'!$O$40 -> 0.0069288452
D37: Bank deposits | E37: ='Full 3 FS Model & DCF'!J30/'Full 3 FS Model & DCF'!$J$40 -> 0.069214166 | F37: ='Full 3 FS Model & DCF'!K30/'Full 3 FS Model & DCF'!$K$40 -> 0.10028459 | G37: ='Full 3 FS Model & DCF'!L30/'Full 3 FS Model & DCF'!$L$40 -> 0.025579326 | H37: ='Full 3 FS Model & DCF'!M30/'Full 3 FS Model & DCF'!$M$40 -> 0.01311668 | I37: ='Full 3 FS Model & DCF'!N30/'Full 3 FS Model & DCF'!$N$40 -> 0.027690859 | J37: ='Full 3 FS Model & DCF'!O30/'Full 3 FS Model & DCF'!$O$40 -> 0.024365129
D38: Accounts Receivables | E38: ='Full 3 FS Model & DCF'!J31/'Full 3 FS Model & DCF'!$J$40 -> 0.087009742 | F38: ='Full 3 FS Model & DCF'!K31/'Full 3 FS Model & DCF'!$K$40 -> 0.05177222 | G38: ='Full 3 FS Model & DCF'!L31/'Full 3 FS Model & DCF'!$L$40 -> 0.052598675 | H38: ='Full 3 FS Model & DCF'!M31/'Full 3 FS Model & DCF'!$M$40 -> 0.062159587 | I38: ='Full 3 FS Model & DCF'!N31/'Full 3 FS Model & DCF'!$N$40 -> 0.05942862 | J38: ='Full 3 FS Model & DCF'!O31/'Full 3 FS Model & DCF'!$O$40 -> 0.054981504
D39: Inventory | E39: ='Full 3 FS Model & DCF'!J32/'Full 3 FS Model & DCF'!$J$40 -> 0.14748434 | F39: ='Full 3 FS Model & DCF'!K32/'Full 3 FS Model & DCF'!$K$40 -> 0.15988377 | G39: ='Full 3 FS Model & DCF'!L32/'Full 3 FS Model & DCF'!$L$40 -> 0.15559163 | H39: ='Full 3 FS Model & DCF'!M32/'Full 3 FS Model & DCF'!$M$40 -> 0.14824558 | I39: ='Full 3 FS Model & DCF'!N32/'Full 3 FS Model & DCF'!$N$40 -> 0.12874504 | J39: ='Full 3 FS Model & DCF'!O32/'Full 3 FS Model & DCF'!$O$40 -> 0.14233372
D40: Other Current Assets | E40: ='Full 3 FS Model & DCF'!J33/'Full 3 FS Model & DCF'!$J$40 -> 0.050079057 | F40: ='Full 3 FS Model & DCF'!K33/'Full 3 FS Model & DCF'!$K$40 -> 0.035710829 | G40: ='Full 3 FS Model & DCF'!L33/'Full 3 FS Model & DCF'!$L$40 -> 0.024267107 | H40: ='Full 3 FS Model & DCF'!M33/'Full 3 FS Model & DCF'!$M$40 -> 0.020846806 | I40: ='Full 3 FS Model & DCF'!N33/'Full 3 FS Model & DCF'!$N$40 -> 0.030316055 | J40: ='Full 3 FS Model & DCF'!O33/'Full 3 FS Model & DCF'!$O$40 -> 0.03924943
C42: Non-current Assets:
D43: Property, plant and equipment | E43: ='Full 3 FS Model & DCF'!J36/'Full 3 FS Model & DCF'!$J$40 -> 0.22057706 | F43: ='Full 3 FS Model & DCF'!K36/'Full 3 FS Model & DCF'!$K$40 -> 0.1893782 | G43: ='Full 3 FS Model & DCF'!L36/'Full 3 FS Model & DCF'!$L$40 -> 0.18106106 | H43: ='Full 3 FS Model & DCF'!M36/'Full 3 FS Model & DCF'!$M$40 -> 0.24523504 | I43: ='Full 3 FS Model & DCF'!N36/'Full 3 FS Model & DCF'!$N$40 -> 0.2408376 | J43: ='Full 3 FS Model & DCF'!O36/'Full 3 FS Model & DCF'!$O$40 -> 0.2322769
D44: Goodwill | E44: ='Full 3 FS Model & DCF'!J37/'Full 3 FS Model & DCF'!$J$40 -> 0.035917216 | F44: ='Full 3 FS Model & DCF'!K37/'Full 3 FS Model & DCF'!$K$40 -> 0.030976857 | G44: ='Full 3 FS Model & DCF'!L37/'Full 3 FS Model & DCF'!$L$40 -> 0.020444413 | H44: ='Full 3 FS Model & DCF'!M37/'Full 3 FS Model & DCF'!$M$40 -> 0.029679143 | I44: ='Full 3 FS Model & DCF'!N37/'Full 3 FS Model & DCF'!$N$40 -> 0.026788902 | J44: ='Full 3 FS Model & DCF'!O37/'Full 3 FS Model & DCF'!$O$40 -> 0.025067482
D45: Financial Assets | E45: ='Full 3 FS Model & DCF'!J38/'Full 3 FS Model & DCF'!$J$40 -> 0.36020274 | F45: ='Full 3 FS Model & DCF'!K38/'Full 3 FS Model & DCF'!$K$40 -> 0.3953525 | G45: ='Full 3 FS Model & DCF'!L38/'Full 3 FS Model & DCF'!$L$40 -> 0.5111673 | H45: ='Full 3 FS Model & DCF'!M38/'Full 3 FS Model & DCF'!$M$40 -> 0.46319383 | I45: ='Full 3 FS Model & DCF'!N38/'Full 3 FS Model & DCF'!$N$40 -> 0.4626184 | J45: ='Full 3 FS Model & DCF'!O38/'Full 3 FS Model & DCF'!$O$40 -> 0.46616827
D46: Other Non-current Assets | E46: ='Full 3 FS Model & DCF'!J39/'Full 3 FS Model & DCF'!$J$40 -> 0.01198951 | F46: ='Full 3 FS Model & DCF'!K39/'Full 3 FS Model & DCF'!$K$40 -> 0.014401966 | G46: ='Full 3 FS Model & DCF'!L39/'Full 3 FS Model & DCF'!$L$40 -> 0.0084586061 | H46: ='Full 3 FS Model & DCF'!M39/'Full 3 FS Model & DCF'!$M$40 -> 0.0067707261 | I46: ='Full 3 FS Model & DCF'!N39/'Full 3 FS Model & DCF'!$N$40 -> 0.0072017658 | J46: ='Full 3 FS Model & DCF'!O39/'Full 3 FS Model & DCF'!$O$40 -> 0.0086287236
D47: Total Assets | E47: ='Full 3 FS Model & DCF'!J40/'Full 3 FS Model & DCF'!$J$40 -> 1 | F47: ='Full 3 FS Model & DCF'!K40/'Full 3 FS Model & DCF'!$K$40 -> 1 | G47: ='Full 3 FS Model & DCF'!L40/'Full 3 FS Model & DCF'!$L$40 -> 1 | H47: ='Full 3 FS Model & DCF'!M40/'Full 3 FS Model & DCF'!$M$40 -> 1 | I47: ='Full 3 FS Model & DCF'!N40/'Full 3 FS Model & DCF'!$N$40 -> 1 | J47: ='Full 3 FS Model & DCF'!O40/'Full 3 FS Model & DCF'!$O$40 -> 1
B50: Liability
C51: Current Liabilities
D52: Accounts Payable | E52: ='Full 3 FS Model & DCF'!J44/'Full 3 FS Model & DCF'!$J$40 -> 0.15845076 | F52: ='Full 3 FS Model & DCF'!K44/'Full 3 FS Model & DCF'!$K$40 -> 0.17656836 | G52: ='Full 3 FS Model & DCF'!L44/'Full 3 FS Model & DCF'!$L$40 -> 0.16426758 | H52: ='Full 3 FS Model & DCF'!M44/'Full 3 FS Model & DCF'!$M$40 -> 0.16013994 | I52: ='Full 3 FS Model & DCF'!N44/'Full 3 FS Model & DCF'!$N$40 -> 0.16013762 | J52: ='Full 3 FS Model & DCF'!O44/'Full 3 FS Model & DCF'!$O$40 -> 0.17483561
D53: Other Current Liabilities | E53: ='Full 3 FS Model & DCF'!J45/'Full 3 FS Model & DCF'!$J$40 -> 0.072427761 | F53: ='Full 3 FS Model & DCF'!K45/'Full 3 FS Model & DCF'!$K$40 -> 0.059370543 | G53: ='Full 3 FS Model & DCF'!L45/'Full 3 FS Model & DCF'!$L$40 -> 0.054086725 | H53: ='Full 3 FS Model & DCF'!M45/'Full 3 FS Model & DCF'!$M$40 -> 0.05069659 | I53: ='Full 3 FS Model & DCF'!N45/'Full 3 FS Model & DCF'!$N$40 -> 0.056198372 | J53: ='Full 3 FS Model & DCF'!O45/'Full 3 FS Model & DCF'!$O$40 -> 0.063656019
C54: Non-Current Liabilities
D55: Debt | E55: ='Full 3 FS Model & DCF'!J47/'Full 3 FS Model & DCF'!$J$40 -> 0.04993901 | F55: ='Full 3 FS Model & DCF'!K47/'Full 3 FS Model & DCF'!$K$40 -> 0.046930386 | G55: ='Full 3 FS Model & DCF'!L47/'Full 3 FS Model & DCF'!$L$40 -> 0.083853432 | H55: ='Full 3 FS Model & DCF'!M47/'Full 3 FS Model & DCF'!$M$40 -> 0.08596442 | I55: ='Full 3 FS Model & DCF'!N47/'Full 3 FS Model & DCF'!$N$40 -> 0.09026773 | J55: ='Full 3 FS Model & DCF'!O47/'Full 3 FS Model & DCF'!$O$40 -> 0.054336082
D56: Other Non-Current Liabilities | E56: ='Full 3 FS Model & DCF'!J48/'Full 3 FS Model & DCF'!$J$40 -> 0.0090902191 | F56: ='Full 3 FS Model & DCF'!K48/'Full 3 FS Model & DCF'!$K$40 -> 0.0072452345 | G56: ='Full 3 FS Model & DCF'!L48/'Full 3 FS Model & DCF'!$L$40 -> 0.01222676 | H56: ='Full 3 FS Model & DCF'!M48/'Full 3 FS Model & DCF'!$M$40 -> 0.011740564 | I56: ='Full 3 FS Model & DCF'!N48/'Full 3 FS Model & DCF'!$N$40 -> 0.012096401 | J56: ='Full 3 FS Model & DCF'!O48/'Full 3 FS Model & DCF'!$O$40 -> 0.01346722
D57: Total Liabilities | E57: ='Full 3 FS Model & DCF'!J49/'Full 3 FS Model & DCF'!$J$40 -> 0.28990775 | F57: ='Full 3 FS Model & DCF'!K49/'Full 3 FS Model & DCF'!$K$40 -> 0.29011453 | G57: ='Full 3 FS Model & DCF'!L49/'Full 3 FS Model & DCF'!$L$40 -> 0.3144345 | H57: ='Full 3 FS Model & DCF'!M49/'Full 3 FS Model & DCF'!$M$40 -> 0.30854151 | I57: ='Full 3 FS Model & DCF'!N49/'Full 3 FS Model & DCF'!$N$40 -> 0.31870012 | J57: ='Full 3 FS Model & DCF'!O49/'Full 3 FS Model & DCF'!$O$40 -> 0.30629493
B59: Shareholder's Equity
C60: Equity Capital | E60: ='Full 3 FS Model & DCF'!J52/'Full 3 FS Model & DCF'!$J$40 -> 0.018891363 | F60: ='Full 3 FS Model & DCF'!K52/'Full 3 FS Model & DCF'!$K$40 -> 0.016293711 | G60: ='Full 3 FS Model & DCF'!L52/'Full 3 FS Model & DCF'!$L$40 -> 0.014391271 | H60: ='Full 3 FS Model & DCF'!M52/'Full 3 FS Model & DCF'!$M$40 -> 0.012976066 | I60: ='Full 3 FS Model & DCF'!N52/'Full 3 FS Model & DCF'!$N$40 -> 0.0117175 | J60: ='Full 3 FS Model & DCF'!O52/'Full 3 FS Model & DCF'!$O$40 -> 0.010967217
C61: Retained Earnings | E61: ='Full 3 FS Model & DCF'!J53/'Full 3 FS Model & DCF'!$J$40 -> 0.68730309 | F61: ='Full 3 FS Model & DCF'!K53/'Full 3 FS Model & DCF'!$K$40 -> 0.6902093 | G61: ='Full 3 FS Model & DCF'!L53/'Full 3 FS Model & DCF'!$L$40 -> 0.66787333 | H61: ='Full 3 FS Model & DCF'!M53/'Full 3 FS Model & DCF'!$M$40 -> 0.64419523 | I61: ='Full 3 FS Model & DCF'!N53/'Full 3 FS Model & DCF'!$N$40 -> 0.64069993 | J61: ='Full 3 FS Model & DCF'!O53/'Full 3 FS Model & DCF'!$O$40 -> 0.65739314
C62: Total Shareholder's Equity | E62: ='Full 3 FS Model & DCF'!J54/'Full 3 FS Model & DCF'!$J$40 -> 0.70619446 | F62: ='Full 3 FS Model & DCF'!K54/'Full 3 FS Model & DCF'!$K$40 -> 0.70650301 | G62: ='Full 3 FS Model & DCF'!L54/'Full 3 FS Model & DCF'!$L$40 -> 0.6822646 | H62: ='Full 3 FS Model & DCF'!M54/'Full 3 FS Model & DCF'!$M$40 -> 0.65717129 | I62: ='Full 3 FS Model & DCF'!N54/'Full 3 FS Model & DCF'!$N$40 -> 0.65241743 | J62: ='Full 3 FS Model & DCF'!O54/'Full 3 FS Model & DCF'!$O$40 -> 0.66836036
C63: Non-controlling Interest | E63: ='Full 3 FS Model & DCF'!J55/'Full 3 FS Model & DCF'!$J$40 -> 0.0038977936 | F63: ='Full 3 FS Model & DCF'!K55/'Full 3 FS Model & DCF'!$K$40 -> 0.0033824615 | G63: ='Full 3 FS Model & DCF'!L55/'Full 3 FS Model & DCF'!$L$40 -> 0.0033008996 | H63: ='Full 3 FS Model & DCF'!M55/'Full 3 FS Model & DCF'!$M$40 -> 0.034287192 | I63: ='Full 3 FS Model & DCF'!N55/'Full 3 FS Model & DCF'!$N$40 -> 0.028882447 | J63: ='Full 3 FS Model & DCF'!O55/'Full 3 FS Model & DCF'!$O$40 -> 0.02534471
C64: Total Liabilities & Shareholder's Equity | E64: ='Full 3 FS Model & DCF'!J56/'Full 3 FS Model & DCF'!$J$40 -> 1 | F64: ='Full 3 FS Model & DCF'!K56/'Full 3 FS Model & DCF'!$K$40 -> 1 | G64: ='Full 3 FS Model & DCF'!L56/'Full 3 FS Model & DCF'!$L$40 -> 1 | H64: ='Full 3 FS Model & DCF'!M56/'Full 3 FS Model & DCF'!$M$40 -> 1 | I64: ='Full 3 FS Model & DCF'!N56/'Full 3 FS Model & DCF'!$N$40 -> 1 | J64: ='Full 3 FS Model & DCF'!O56/'Full 3 FS Model & DCF'!$O$40 -> 1
C68: Back to cover

Sheet WACC Calculation
B1: Dabur India Ltd.
B4: Weighted Average Cost of Capital - WACC
B6: Comparable Companies Beta
B7: (Amounts in crores)
G8: Equity | H8: Total | I8: Debt/ | J8: Debt/ | K8: Tax | L8: Levered | M8: Unlevered
B9: Name | G9: Value | H9: Debt | I9: Equity | J9: Capital | K9: Rate (%) | L9: Beta | M9: Beta
B10: ='Comp value data'!B6 -> Godrej Consumer | G10: ='Comp- Valuation- Dabur'!F11 -> 114771.36 | H10: ='Comp- Valuation- Dabur'!G11 -> 4113.49 | I10: =H10/G10 -> 0.035840737 | J10: =H10/(G10+H10) -> 0.034600625 | K10: ='Comp value data'!P6 -> 0.27883089 | L10: 0.23 | M10: =L10/(1+I10*(1-K10)) -> 0.22420492
B11: ='Comp value data'!B7 -> Colgate-Palmoliv | G11: ='Comp- Valuation- Dabur'!F12 -> 58947.84 | H11: ='Comp- Valuation- Dabur'!G12 -> 59.99 | I11: =H11/G11 -> 0.0010176794 | J11: =H11/(G11+H11) -> 0.0010166447 | K11: ='Comp value data'!P7 -> 0.25693102 | L11: 0.31 | M11: =L11/(1+I11*(1-K11)) -> 0.30976575
B12: ='Comp value data'!B8 -> P & G Hygiene | G12: ='Comp- Valuation- Dabur'!F13 -> 42815.5 | H12: ='Comp- Valuation- Dabur'!G13 -> 2.06 | I12: =H12/G12 -> 4.8113417e-05 | J12: =H12/(G12+H12) -> 4.8111102e-05 | K12: ='Comp value data'!P8 -> 0.26410391 | L12: 0.46 | M12: =L12/(1+I12*(1-K12)) -> 0.45998371 | O12: For levered beta, data extracted from investing.com
B13: ='Comp value data'!B9 -> Gillette India | G13: ='Comp- Valuation- Dabur'!F14 -> 27646.43 | H13: ='Comp- Valuation- Dabur'!G14 -> 0.05 | I13: =H13/G13 -> 1.8085518e-06 | J13: =H13/(G13+H13) -> 1.8085485e-06 | K13: ='Comp value data'!P9 -> 0.24973531 | L13: 0.03 | M13: =L13/(1+I13*(1-K13)) -> 0.029999959
B14: ='Comp value data'!B10 -> Emami | G14: ='Comp- Valuation- Dabur'!F15 -> 22440.465 | H14: ='Comp- Valuation- Dabur'!G15 -> 89.79 | I14: =H14/G14 -> 0.004001254 | J14: =H14/(G14+H14) -> 0.0039853078 | K14: ='Comp value data'!P10 -> 0.095151011 | L14: 0.05 | M14: =L14/(1+I14*(1-K14)) -> 0.049819627
B15: Honasa Consumer | G15: ='Comp- Valuation- Dabur'!F16 -> 8914.333 | H15: ='Comp- Valuation- Dabur'!G16 -> 109.79 | I15: =H15/G15 -> 0.012316121 | J15: =H15/(G15+H15) -> 0.012166279 | K15: ='Comp value data'!P11 -> 0.24517497 | L15: 0.8 | M15: =L15/(1+I15*(1-K15)) -> 0.79263129
B16: Average | I16: =AVERAGE(I10:I15) -> 0.0088709521 | J16: =AVERAGE(J10:J15) -> 0.0086364627 | K16: =AVERAGE(K10:K15) -> 0.23165452 | L16: =AVERAGE(L10:L15) -> 0.31333333 | M16: =AVERAGE(M10:M15) -> 0.31106754
B17: Median | I17: =MEDIAN(I10:I15) -> 0.0025094667 | J17: =MEDIAN(J10:J15) -> 0.0025009762 | K17: =MEDIAN(K10:K15) -> 0.25333316 | L17: =MEDIAN(L10:L15) -> 0.27 | M17: =MEDIAN(M10:M15) -> 0.26698534
B19: Dabur India | G19: ='Comp- Valuation- Dabur'!F10 -> 91992.95 | H19: ='Comp- Valuation- Dabur'!G10 -> 950.37
B22: WACC Calculation
B24: Target Capital Structure
B25: Proportion of Debt | H25: =J16 -> 0.0086364627
B26: Proportion of Equity | H26: =1-H25 -> 0.99136354
B28: Current Capital Structure
B29: Market Cap | H29: =G19 -> 91992.95
B30: Total Debt | H30: =H19 -> 950.37
B31: Debt/Equity | H31: =H30/H29 -> 0.0103309
B33: Cost of Debt
B34: Pre-Tax Cost of debt | H34: =M35/M34 -> 0.032556621 | K34: Total Debt | M34: =703.58+4318.44 -> 5022.02 | O34: (Source: Annual Report)
B35: Tax Rate | H35: ='Comp value data'!P5 -> 0.22710216 | K35: Interest | M35: =-'Full 3 FS Model & DCF'!O108 -> 163.5
B36: After Tax Cost of Debt | H36: =H34*(1-H35) -> 0.025162942
B38: Cost of Equity
B39: Risk-Free Rate | H39: 0.06521
B40: Equity Market Return | H40: ='Market Data'!F13 -> 0.124
B41: Equity Risk Premium | H41: =H40-H39 -> 0.05879
B42: Levered Beta | H42: =M16*(1+H31*(1-H35)) -> 0.31355133
B43: Cost of equity | H43: =H39+(H41*H42) -> 0.083643683
B45: WACC | H45: =H36*H25+H43*H26 -> 0.083138616
B48: Back to cover

Sheet Football Field Analysis
B1: Dabur India Ltd.
B4: Valuation Summary - Football Field
B6: Football Field Data
J7: Market
G8: Comps | H8: DCF | I8: 52-week High/low | J8: Consesus
B9: High | G9: =MAX('Comp- Valuation- Dabur'!L23:L25) -> 595.79162 | H9: 736.11697 | I9: 529.4 | J9: 625
B10: High | G10: =MAX('Comp- Valuation- Dabur'!L24:L26) -> 595.79162 | H10: 736.11697 | I10: 529.4 | J10: 625
B11: Low | G11: =MIN('Comp- Valuation- Dabur'!L23:L25) -> 553.91433 | H11: 437.95659 | I11: 484.15 | J11: 400
B12: Low | G12: =MIN('Comp- Valuation- Dabur'!L23:L25) -> 553.91433 | H12: 437.95659 | I12: 484.15 | J12: 400
B14: Valuation Summary
B32: Back to cover

Sheet Recommendation
B1: Dabur India Ltd.
B4: Recommendation
B11: Various valuation methodologies have been applied to determine the intrinsic value of Dabur India Ltd., combining both DCF-FCFF and Multiple-Based Relative Valuation approaches. Under the DCF method, the equity value per share was estimated at ₹573.36. Under Relative Valuation, the equity value per share was computed as ₹553.90 using EV/Revenue multiples, ₹577.80 under EV/EBITDA multiples, and ₹595.80 using P/E multiples. To incorporate both long-term cash flow potential and current market-based pricing, the DCF valuation was assigned an 80% weight, while the remaining 20% was allocated to the blended Relative Valuation outcome. Based on this methodology, the blended fair value per share of Dabur India comes out to ₹582.39.
B23: With Dabur’s current market price at ₹518.70, the valuation indicates a positive gap of +12.28%, implying that the stock is undervalued. This highlights an opportunity for long-term investors to accumulate the stock, while existing shareholders may continue to hold given the meaningful room for appreciation supported by Dabur’s business fundamentals and steady financial outlook.
B27: In terms of operational performance, Dabur has maintained or expanded market share in more than 85% of its portfolio, driven by its leadership in Health Care, Oral Care, Digestives, and several Personal Care categories. Core products such as Chyawanprash, Honey, Real Juices, Odonil, Dabur Amla, and Pudin Hara continue to perform well due to strong brand equity and the company’s heritage in natural and ayurvedic formulations. That said, certain Personal Care and Home Care segments have faced competitive intensity from herbal-focused and D2C brands, impacting volumes in select categories.
B33: Rural markets — traditionally Dabur’s stronghold — have experienced slower recovery, affecting overall volume growth. In contrast, urban markets have remained stable, supported by premiumisation, increasing penetration of modern trade, e-commerce expansion, and a broader shift in consumer preference toward health and wellness. Dabur’s continued investments in deepening its rural distribution (targeting over 100,000 villages), enhancing its digital footprint, and launching natural and health-oriented products position it well to capitalize on medium-term demand improvements.
B38: Key risks include a prolonged rural slowdown, rising competition from FMCG and new-age herbal brands, potential resurgence in commodity inflation, and execution challenges in new product initiatives or international markets. Despite these headwinds, several catalysts — including rural recovery, margin expansion due to moderating input costs, steady innovation pipeline, and distribution expansion — create visible upside opportunities.
B42: Overall, Dabur India remains a fundamentally strong, resilient, and cash-generative FMCG franchise. With the blended fair value at ₹582.39 and the market price at ₹518.70, the stock appears undervalued by +12.28%. Therefore, the valuation supports a Buy / Accumulate recommendation for long-term investors, while existing shareholders may continue to Hold, given the company’s strong brand portfolio, stable cash flows, and favourable industry positioning.

Sheet Market Data
B1: Dabur India Ltd.
B4: Equity Market Return (5 year)
B7: Date | C7: Index Close Price
B8: 44134 | C8: 11642.4 | E8: Market Return
B9: 44137 | C9: 11669.15 | E9: Year | F9: =YEARFRAC(B8,B1248) -> 5
B10: 44138 | C10: 11813.5 | E10: CAGR | F10: =_xlfn.RRI(F9,C8,C1248) -> 0.17179808 | H10: (Calculated)
B11: 44139 | C11: 11908.5
B12: 44140 | C12: 12120.3 | E12: Year | F12: 10
B13: 44141 | C13: 12263.55 | E13: CAGR | F13: 0.124 | H13: (Source : Screener.in)
B14: 44144 | C14: 12461.05
B15: 44145 | C15: 12631.1
B16: 44146 | C16: 12749.15 | E16: Back to cover
B17: 44147 | C17: 12690.8
B18: 44148 | C18: 12719.95
B19: 44149 | C19: 12780.25
B20: 44152 | C20: 12874.2
B21: 44153 | C21: 12938.25
B22: 44154 | C22: 12771.7
B23: 44155 | C23: 12859.05
B24: 44158 | C24: 12926.45
B25: 44159 | C25: 13055.15
B26: 44160 | C26: 12858.4
B27: 44161 | C27: 12987
B28: 44162 | C28: 12968.95
... B1248: 45961 | C1248: 25722.1

Sheet Calculation of Beta
B1: Dabur India Ltd.
B4: Company Beta
C6: Index | D6: % Change | E6: Stock | F6: % Change | I6: Min | J6: =MIN(E56:E68) -> 484.15
B7: Date | C7: Closing price | D7: Monthly | E7: Close price | F7: Monthly | I7: Max | J7: =MAX(E56:E68) -> 529.4
B8: 44136 | C8: 44149.72 | E8: 499.6
B9: 44166 | C9: 47751.33 | D9: =C9/C8-1 -> 0.081577188 | E9: 534 | F9: =E9/E8-1 -> 0.068855084 | I9: Beta | J9: =SLOPE(F9:F68,D9:D68) -> 0.61363702 | L9: Using Slope function
B10: 44197 | C10: 46285.77 | D10: =C10/C9-1 -> -0.030691501 | E10: 515.25 | F10: =E10/E9-1 -> -0.03511236
B11: 44228 | C11: 49099.99 | D11: =C11/C10-1 -> 0.060800976 | E11: 503.35 | F11: =E11/E10-1 -> -0.023095585 | J11: SUMMARY OUTPUT
B12: 44256 | C12: 49509.15 | D12: =C12/C11-1 -> 0.0083331993 | E12: 540.7 | F12: =E12/E11-1 -> 0.074202841 | N12: Beta | O12: =K28 -> 0.61363702
B13: 44287 | C13: 48782.36 | D13: =C13/C12-1 -> -0.014679913 | E13: 538.45 | F13: =E13/E12-1 -> -0.0041612724 | J13: Regression Statistics | N13: Using Regression Beta come same as per the slope function
B14: 44317 | C14: 51937.44 | D14: =C14/C13-1 -> 0.064676658 | E14: 540.4 | F14: =E14/E13-1 -> 0.0036215062 | J14: Multiple R | K14: 0.43572493
B15: 44348 | C15: 52482.71 | D15: =C15/C14-1 -> 0.010498592 | E15: 568.8 | F15: =E15/E14-1 -> 0.052553664 | J15: R Square | K15: 0.18985621
B16: 44378 | C16: 52586.84 | D16: =C16/C15-1 -> 0.001984082 | E16: 600.5 | F16: =E16/E15-1 -> 0.055731364 | J16: Adjusted R Square | K16: 0.17588822
B17: 44409 | C17: 57552.39 | D17: =C17/C16-1 -> 0.094425716 | E17: 620.85 | F17: =E17/E16-1 -> 0.033888426 | J17: Standard Error | K17: 0.046907301
B18: 44440 | C18: 59126.36 | D18: =C18/C17-1 -> 0.027348473 | E18: 617.1 | F18: =E18/E17-1 -> -0.0060401063 | J18: Observations | K18: 60
B19: 44470 | C19: 59306.93 | D19: =C19/C18-1 -> 0.0030539678 | E19: 586.3 | F19: =E19/E18-1 -> -0.049910873
B20: 44501 | C20: 57064.87 | D20: =C20/C19-1 -> -0.037804351 | E20: 595.4 | F20: =E20/E19-1 -> 0.015521064 | J20: ANOVA
B21: 44531 | C21: 58253.82 | D21: =C21/C20-1 -> 0.02083506 | E21: 580.4 | F21: =E21/E20-1 -> -0.025193147 | K21: df | L21: SS | M21: MS | N21: F | O21: Significance F
B22: 44562 | C22: 58014.17 | D22: =C22/C21-1 -> -0.0041138933 | E22: 537.25 | F22: =E22/E21-1 -> -0.074345279 | J22: Regression | K22: 1 | L22: 0.029906913 | M22: 0.029906913 | N22: 13.59223 | O22: 0.00050190976
B23: 44593 | C23: 56247.28 | D23: =C23/C22-1 -> -0.03045618 | E23: 563.75 | F23: =E23/E22-1 -> 0.049325268 | J23: Residual | K23: 58 | L23: 0.1276171 | M23: 0.0022002948
B24: 44621 | C24: 58568.51 | D24: =C24/C23-1 -> 0.041268307 | E24: 536.55 | F24: =E24/E23-1 -> -0.048248337 | J24: Total | K24: 59 | L24: 0.15752401
B25: 44652 | C25: 57060.87 | D25: =C25/C24-1 -> -0.025741478 | E25: 556.85 | F25: =E25/E24-1 -> 0.037834312
B26: 44682 | C26: 55566.41 | D26: =C26/C25-1 -> -0.026190628 | E26: 518.75 | F26: =E26/E25-1 -> -0.06842058 | K26: Coefficients | L26: Standard Error | M26: t Stat | N26: P-value | O26: Lower 95% | P26: Upper 95% | Q26: Lower 95.0% | R26: Upper 95.0%
B27: 44713 | C27: 53018.94 | D27: =C27/C26-1 -> -0.045845503 | E27: 495.95 | F27: =E27/E26-1 -> -0.043951807 | J27: Intercept | K27: -0.0049956732 | L27: 0.0063396393 | M27: -0.78800589 | N27: 0.43390207 | O27: -0.01768584 | P27: 0.0076944938 | Q27: -0.01768584 | R27: 0.0076944938
B28: 44743 | C28: 57570.25 | D28: =C28/C27-1 -> 0.085843097 | E28: 584.15 | F28: =E28/E27-1 -> 0.17784051 | J28: X Variable 1 | K28: 0.61363702 | L28: 0.16644325 | M28: 3.6867641 | N28: 0.00050190976 | O28: 0.28046465 | P28: 0.94680939 | Q28: 0.28046465 | R28: 0.94680939
B29: 44774 | C29: 59537.07 | D29: =C29/C28-1 -> 0.034163826 | E29: 583.4 | F29: =E29/E28-1 -> -0.0012839168
B30: 44805 | C30: 57426.92 | D30: =C30/C29-1 -> -0.035442624 | E30: 572.55 | F30: =E30/E29-1 -> -0.018597875
B31: 44835 | C31: 60746.59 | D31: =C31/C30-1 -> 0.057806861 | E31: 554.55 | F31: =E31/E30-1 -> -0.031438302
B32: 44866 | C32: 63099.65 | D32: =C32/C31-1 -> 0.038735672 | E32: 589.15 | F32: =E32/E31-1 -> 0.062392931
B33: 44896 | C33: 60840.74 | D33: =C33/C32-1 -> -0.035799089 | E33: 561.4 | F33: =E33/E32-1 -> -0.047101757
B34: 44927 | C34: 59549.9 | D34: =C34/C33-1 -> -0.021216704 | E34: 557.65 | F34: =E34/E33-1 -> -0.0066797292
B35: 44958 | C35: 58962.12 | D35: =C35/C34-1 -> -0.0098703776 | E35: 533.05 | F35: =E35/E34-1 -> -0.044113691
B36: 44986 | C36: 58991.52 | D36: =C36/C35-1 -> 0.00049862522 | E36: 545.1 | F36: =E36/E35-1 -> 0.022605759
B37: 45017 | C37: 61112.44 | D37: =C37/C36-1 -> 0.035952964 | E37: 532.85 | F37: =E37/E36-1 -> -0.022472941
B38: 45047 | C38: 62622.24 | D38: =C38/C37-1 -> 0.024705281 | E38: 554.6 | F38: =E38/E37-1 -> 0.040818242
B39: 45078 | C39: 64718.56 | D39: =C39/C38-1 -> 0.033475647 | E39: 572.9 | F39: =E39/E38-1 -> 0.032996754
B40: 45108 | C40: 66527.67 | D40: =C40/C39-1 -> 0.027953496 | E40: 575.55 | F40: =E40/E39-1 -> 0.0046255891
... B68: 45962 | C68: 83216.28 | D68: =C68/C67-1 -> -0.0086066369 | E68: 518.8 | F68: =E68/E67-1 -> 0.06333265
B70: Back to cover

Sheet Comp value data
B2: (Source: Screener.in)
B4: Name | C4: CMP Rs. | D4: No. Eq. Shares Cr. | E4: Market Cap | F4: Debt Rs.Cr. | G4: Cash Rs.Cr. | H4: Sales Rs.Cr. | I4: EBITDA | J4: PAT 12M Rs.Cr. | K4: EBIT 12M Rs.Cr. | L4: Interest | M4: Dep 12M Rs.Cr. | N4: EBT | O4: Tax 12M Rs.Cr. | P4: Tax Rate
B5: Dabur India | C5: 518.65 | D5: 177.37 | E5: =C5*D5 -> 91992.95 | F5: 950.37 | G5: 578.01 | H5: 12781.29 | I5: =K5+M5 -> 2917.94 | J5: 1808.97 | K5: 2462.89 | L5: 157.76 | M5: 455.05 | N5: =K5-L5 -> 2305.13 | O5: 523.5 | P5: =O5/N5 -> 0.22710216
B6: Godrej Consumer | C6: 1121.8 | D6: 102.31 | E6: =C6*D6 -> 114771.36 | F6: 4113.49 | G6: 1080.34 | H6: 14853.33 | I6: =K6+M6 -> 3247.18 | J6: 1882.61 | K6: 2987.75 | L6: 341.63 | M6: 259.43 | N6: =K6-L6 -> 2646.12 | O6: 737.82 | P6: =O6/N6 -> 0.27883089
B7: Colgate-Palmoliv | C7: 2167.2 | D7: 27.2 | E7: =C7*D7 -> 58947.84 | F7: 59.99 | G7: 1347.47 | H7: 5877.91 | I7: =K7+M7 -> 1942.8 | J7: 1325.91 | K7: 1788.57 | L7: 4.2 | M7: 154.23 | N7: =K7-L7 -> 1784.37 | O7: 458.46 | P7: =O7/N7 -> 0.25693102
B8: P & G Hygiene | C8: 13174 | D8: 3.25 | E8: =C8*D8 -> 42815.5 | F8: 2.06 | G8: 793.12 | H8: 4326.46 | I8: =K8+M8 -> 1177.94 | J8: 826.61 | K8: 1139.33 | L8: 16.06 | M8: 38.61 | N8: =K8-L8 -> 1123.27 | O8: 296.66 | P8: =O8/N8 -> 0.26410391
B9: Gillette India | C9: 8480.5 | D9: 3.26 | E9: =C9*D9 -> 27646.43 | F9: 0.05 | G9: 591.52 | H9: 2970.55 | I9: =K9+M9 -> 862.8 | J9: 573.99 | K9: 777.62 | L9: 12.57 | M9: 85.18 | N9: =K9-L9 -> 765.05 | O9: 191.06 | P9: =O9/N9 -> 0.24973531
B10: Emami | C10: 514.1 | D10: 43.65 | E10: =C10*D10 -> 22440.465 | F10: 89.79 | G10: 272.9 | H10: 3807.21 | I10: =K10+M10 -> 1090.24 | J10: 818.08 | K10: 911.96 | L10: 9.71 | M10: 178.28 | N10: =K10-L10 -> 902.25 | O10: 85.85 | P10: =O10/N10 -> 0.095151011
B11: Honasa Consumer | C11: 273.95 | D11: 32.54 | E11: =C11*D11 -> 8914.333 | F11: 109.79 | G11: 294.99 | H11: 1994.23 | I11: =K11+M11 -> 141.55 | J11: 71.17 | K11: 104.95 | L11: 10.65 | M11: 36.6 | N11: =K11-L11 -> 94.3 | O11: 23.12 | P11: =O11/N11 -> 0.24517497
B14: Back to cover

Sheet Historical Statement
B1: Dabur India Ltd.
B4: Historical Financial Information
A6: # | B6: Income Statement | H6: 2020 | I6: =H6+1 -> 2021 | J6: =I6+1 -> 2022 | K6: =J6+1 -> 2023 | L6: =K6+1 -> 2024 | M6: =L6+1 -> 2025
B8: Income
B9: Revenue from operations | H9: 8703.59 | I9: 9561.65 | J9: 10888.68 | K9: 11529.89 | L9: 12404.01 | M9: 12563.09
B10: Other income | H10: 305.29 | I10: 325.29 | J10: 393.16 | K10: 445.39 | L10: 482.41 | M10: 550.1
B11: Total income | H11: 9008.88 | I11: 9886.94 | J11: 11281.84 | K11: 11975.28 | L11: 12886.42 | M11: 13113.19
B12: Expenses
B13: Cost of materials consumed | H13: 3731.71 | I13: 4013.63 | J13: 4766.12 | K13: 5306.97 | L13: 5186.9 | M13: 5263.68
B14: Excise duty | H14: 18.95 | I14: =0 -> 0 | J14: =0 -> 0 | K14: =0 -> 0 | L14: =0 -> 0 | M14: =0 -> 0
B15: Purchases of stock-in-trade | H15: 674.62 | I15: 982.53 | J15: 882.12 | K15: 1052.49 | L15: 1211.11 | M15: 1328.28
B16: Changes in inventories of finished goods, stock-in-trade and work-in-progress | H16: -65.04 | I16: -207.2 | J16: -8.55 | K16: -90.79 | L16: 48.95 | M16: -57.1
B17: Employee benefits expense | H17: 947.74 | I17: 1033.46 | J17: 1079.95 | K17: 1137 | L17: 1239.56 | M17: 1291.23
B18: Finance costs | H18: 49.54 | I18: 30.81 | J18: 38.6 | K18: 78.24 | L18: 124.18 | M18: 163.5
B19: Depreciation and amortisation expense | H19: 220.45 | I19: 240.13 | J19: 252.89 | K19: 310.96 | L19: 399.21 | M19: 445.6
B20: Other expenses | H20: =649.98+953.28 -> 1603.26 | I20: =784.36+952.19 -> 1736.55 | J20: =777.94+1137.29 -> 1915.23 | K20: =640.27+1319.83 -> 1960.1 | L20: =849.06+1468.2 -> 2317.26 | M20: =864.64+1556.02 -> 2420.66
B21: Total expenses | H21: 7181.23 | I21: 7829.91 | J21: 8926.36 | K21: 9754.97 | L21: 10527.17 | M21: 10855.85
B23: Profit before share of loss from joint venture, exceptional items and tax | H23: 1827.65 | I23: 2057.03 | J23: 2355.48 | K23: 2220.31 | L23: 2359.25 | M23: 2257.34
B24: Share of loss of joint venture | H24: -0.01 | I24: -1.01 | J24: -1.8 | K24: -1.63 | L24: -0.51 | M24: 0.55
B25: Profit before exceptional items and tax | H25: 1827.64 | I25: 2056.02 | J25: 2353.68 | K25: 2218.68 | L25: 2358.74 | M25: 2257.89
B26: Exceptional Item | H26: -100 | J26: -85
B27: Profit before tax | H27: =SUM(H25:H26) -> 1727.64 | I27: =SUM(I25:I26) -> 2056.02 | J27: =SUM(J25:J26) -> 2268.68 | K27: =SUM(K25:K26) -> 2218.68 | L27: =SUM(L25:L26) -> 2358.74 | M27: =SUM(M25:M26) -> 2257.89
B28: Tax expense
B29: Current tax | H29: 465.42 | I29: 363.04 | J29: 442.17 | K29: 481.63 | L29: 539.53 | M29: 499.06
B30: Deferred tax | H30: -185.7 | I30: -1.97 | J30: 84.21 | K30: 35.72 | L30: 7.9 | M30: 18.41
B31: Total tax expense | H31: 279.72 | I31: 361.07 | J31: 526.38 | K31: 517.35 | L31: 547.43 | M31: 517.47
B32: Net profit for the year | H32: 1447.92 | I32: 1694.95 | J32: 1742.3 | K32: 1701.33 | L32: 1811.31 | M32: 1740.42
B34: Net profit attributable to:
B35: Owners of the Holding Company | H35: 1444.96 | I35: 1693.3 | J35: 1739.22 | K35: 1707.15 | L35: 1842.68 | M35: 1767.63
B36: Non-controlling interest | H36: 2.96 | I36: 1.65 | J36: 3.08 | K36: -5.82 | L36: -31.37 | M36: -27.21
A39: # | B39: Balancesheet
B41: ASSETS
B42: Non-current assets
B43: a) Property, plant and equipment | H43: 1820.98 | I43: 1811.7 | J43: 1967.95 | K43: 2237.62 | L43: 2560.94 | M43: 2799.88
B44: b) Capital work-in-progress | H44: 146.57 | I44: 147.3 | J44: 167.5 | K44: 171.12 | L44: 209.09 | M44: 166.41
B45: c) Investment property | H45: 51.55 | I45: 50.5 | J45: 49.07 | K45: 47.05 | L45: 45.45 | M45: 43.5
B46: d) Goodwill | H46: 335.97 | I46: 336.01 | J46: 251.15 | K46: 405.25 | L46: 405.12 | M46: 405.09
B47: e) Other intangible assets | H47: 44.18 | I47: 44.71 | J47: 39.73 | K47: 888.73 | L47: 803.49 | M47: 741.22
B48: f) Intangible assets under development | H48: =0 -> 0 | I48: =0 -> 0 | J48: =0 -> 0 | K48: 4.01 | L48: 23.14 | M48: 2.58
B49: g) Investments in joint venture | H49: 12.28 | I49: 11.27 | J49: 9.47 | K49: 7.84 | L49: 7.33 | M49: 7.88
B50: h) Financial assets
B51: (i) Other investments | H51: 1396.95 | I51: 3402.35 | J51: 5355.59 | K51: 5520.95 | L51: 5258.76 | M51: 5372.43
B52: (ii) Loans | H52: 24.64 | I52: 22.48 | J52: =0 -> 0 | K52: =0 -> 0 | L52: =0 -> 0 | M52: =0 -> 0
B53: (iii) Others | H53: 528.48 | I53: 88.65 | J53: 23.32 | K53: 30.39 | L53: 20.83 | M53: 21.39
B54: i) Deferred tax assets (net) | H54: 22 | I54: 17.95 | J54: 0.67 | K54: 2.09 | L54: 6.32 | M54: 2.53
B55: j) Non-current tax assets (net) | H55: 1.09 | I55: 4.29 | J55: 4.5 | K55: 4.49 | L55: 4.45 | M55: 0.61
B56: k) Other non-current assets | H56: 89.06 | I56: 133.98 | J56: 98.74 | K56: 85.87 | L56: 98.14 | M56: 136.3
B57: Total non-current assets | H57: 4473.75 | I57: 6071.19 | J57: 7967.69 | K57: 9405.41 | L57: 9443.06 | M57: 9699.82
B59: Current assets
B60: a) Inventories | H60: 1379.57 | I60: 1734.28 | J60: 1911.37 | K60: 2024.2 | L60: 1946.97 | M60: 2300.11
B61: b) Financial assets
B62: (i) Investments | H62: 1391.03 | I62: 746.01 | J62: 854.56 | K62: 736.47 | L62: 1666.6 | M62: 2087.55
B63: (ii) Trade receivables | H63: 813.89 | I63: 561.58 | J63: 646.15 | K63: 848.75 | L63: 898.72 | M63: 888.5
B64: (iii) Cash and cash equivalents | H64: 163.94 | I64: 241.23 | J64: 255.91 | K64: 146.82 | L64: 247.6 | M64: =184.27-72.3 -> 111.97
B65: (iv) Bank balances other than (iii) above | H65: 647.43 | I65: 1087.8 | J65: 314.23 | K65: 179.1 | L65: 418.76 | M65: 393.74
B66: (v) Loans | H66: 13.07 | I66: =0 -> 0 | J66: =0 -> 0 | K66: =0 -> 0 | L66: =0 -> 0 | M66: =0 -> 0
B67: (v) Others | H67: 2.62 | I67: 17.41 | J67: 36.21 | K67: 28.97 | L67: 42.51 | M67: 44.02
B68: c) Current tax assets (net) | H68: 0.88 | I68: 0.24 | J68: 0.64 | K68: 6.43 | L68: 0.08 | M68: 2.56
B69: d) Other current assets | H69: 467.56 | I69: 387.12 | J69: 297.47 | K69: 278.22 | L69: 458.38 | M69: 631.71
B70: Total current assets | H70: 4880.26 | I70: 4775.67 | J70: 4316.54 | K70: 4248.96 | L70: 5679.62 | M70: 6532.46
B71: Asset held for sale | H71: 0.27 | I71: 0.27 | J71: 0.3 | K71: =0 -> 0 | L71: =0 -> 0 | M71: =0 -> 0
B73: Total assets | H73: 9354.01 | I73: 10847.13 | J73: 12284.53 | K73: 13654.37 | L73: 15122.68 | M73: 16232.28
B75: EQUITY AND LIABILITIES
B76: Equity
B77: a) Equity share capital | H77: 176.71 | I77: 176.74 | J77: 176.79 | K77: 177.18 | L77: 177.2 | M77: 177.23
B78: b) Other equity | H78: 6429.04 | I78: 7486.79 | J78: 8204.51 | K78: 8796.08 | L78: 9689.1 | M78: 10623.46
B79: Equity attributable to shareholders of the Holding Company | H79: 6605.75 | I79: 7663.53 | J79: 8381.3 | K79: 8973.26 | L79: 9866.3 | M79: 10800.69
B80: c) Non-controlling interest | H80: 36.46 | I80: 36.69 | J80: 40.55 | K80: 468.17 | L80: 436.78 | M80: 409.57
B81: Total equity | H81: 6642.21 | I81: 7700.22 | J81: 8421.85 | K81: 9441.43 | L81: 10303.08 | M81: 11210.26
B83: Liabilities
B84: Non-current liabilities
B85: a) Financial liabilities
B86: (i) Borrowings | H86: 162.89 | I86: 1.31 | J86: 250.36 | K86: 298.84 | L86: 535.97 | M86: 304.03
B87: (ii) Lease liabilities | H87: 0 | I87: 132.82 | J87: 139.58 | K87: 144.36 | L87: 170.27 | M87: 181.92
B88: (iii) Other financial liabilities | H88: 4.66 | I88: 1.37 | J88: 4.25 | K88: 4.95 | L88: 5.59 | M88: 1.91
B89: b) Provisions | H89: 62.94 | I89: 63.31 | J89: 63.68 | K89: 64.37 | L89: 68.31 | M89: 71.45
B90: c) Deferred tax liabilities (net) | H90: 17.43 | I90: 13.91 | J90: 82.27 | K90: 90.99 | L90: 109.03 | M90: 144.27
B91: Total non-current liabilities | H91: 247.92 | I91: 212.72 | J91: 540.14 | K91: 603.51 | L91: 889.17 | M91: 703.58
B93: Current liabilities
B94: a) Financial liabilities
B95: (i) Borrowings | H95: 304.24 | I95: 349.14 | J95: 617.29 | K95: 700.18 | L95: 622.1 | M95: =426.09-72.3 -> 353.79
B96: (ii) Lease liabilities | H96: 0 | I96: 25.79 | J96: 22.87 | K96: 30.41 | L96: 36.75 | M96: 38.33
B97: (iii) Trade payables
B98: Due to micro and small enterprises | H98: 44.74 | I98: 117.87 | J98: 147.22 | K98: 165.24 | L98: 184.98 | M98: 132.49
B99: Due to others | H99: 1437.41 | I99: 1797.39 | J99: 1870.73 | K99: 2021.37 | L99: 2236.73 | M99: 2692.85
B100: (iv) Other financial liabilities | H100: 225.52 | I100: 213.14 | J100: 251.95 | K100: 279.84 | L100: 312.6 | M100: 367.1
B101: b) Other current liabilities | H101: 239.78 | I101: 158.44 | J101: 91.42 | K101: 66.7 | L101: 112.35 | M101: 134.15
B102: c) Provisions | H102: 165.54 | I102: 187.84 | J102: 186 | K102: 214.01 | L102: 249.89 | M102: 260.53
B103: d) Current tax liabilities (net) | H103: 46.65 | I103: 84.58 | J103: 135.06 | K103: 131.68 | L103: 175.03 | M103: 266.9
B104: Total current liabilities | H104: 2463.88 | I104: 2934.19 | J104: 3322.54 | K104: 3609.43 | L104: 3930.43 | M104: 4318.44
B106: Total liabilities | H106: 2711.8 | I106: 3146.91 | J106: 3862.68 | K106: 4212.94 | L106: 4819.6 | M106: 5022.02
B108: Total equity and liabilities | H108: 9354.01 | I108: 10847.13 | J108: 12284.53 | K108: 13654.37 | L108: 15122.68 | M108: 16232.28
A110: # | B110: Cashflow statement
B112: Cashflow from operating activities
B113: Profit before tax | H113: 1727.64 | I113: 2056.02 | J113: 2268.68 | K113: 2218.68 | L113: 2358.74 | M113: 2257.89
B114: Adjustments for:
B115: Depreciation and amortisation expense | H115: 220.45 | I115: 240.13 | J115: 252.89 | K115: 310.96 | L115: 399.21 | M115: 445.6
B116: Loss/(gain) on disposal of property, plant and equipment (net) | H116: 3.99 | I116: 0.37 | J116: 0.62 | K116: -14.41 | L116: 1.78 | M116: -6.67
B117: Share based payment expense | H117: 45.26 | I117: 43.3 | J117: 40.02 | K117: 51.23 | L117: 50.43 | M117: 13.5
B118: Provision for disputed liability | H118: 4.5 | I118: 13.5 | J118: 11.5 | K118: 12 | L118: 15 | M118: 10.5
...
